[
  {
    "school":"LSU",
    "record":1.0,
    "schedule":1686.2830015482,
    "results":2.1475714849,
    "elite_wins":22.6807961345,
    "playoff_raw":0.0,
    "record_z":2.21137536,
    "schedule_z":2.0745812014,
    "results_z":2.079187563,
    "elite_wins_z":6.97102349,
    "playoff_z":0.0,
    "wins":14,
    "losses":0,
    "poll_score":2.5063137616,
    "poll_rating":1901.0102018591,
    "rank":1,
    "solver_rating":2195.6893993118,
    "conference":"SEC",
    "abbreviation":"LSU",
    "season":2019,
    "week":17,
    "as_of":"2026-06-21T03:41:18Z"
  },
  {
    "school":"Ohio State",
    "record":0.8821428571,
    "schedule":1631.1266846718,
    "results":2.3185011327,
    "elite_wins":16.3712432913,
    "playoff_raw":0.0,
    "record_z":1.9030087122,
    "schedule_z":1.3891877461,
    "results_z":2.2792584339,
    "elite_wins_z":4.9060677577,
    "playoff_z":0.0,
    "wins":13,
    "losses":1,
    "poll_score":2.0342750795,
    "poll_rating":1825.4840127232,
    "rank":2,
    "solver_rating":2150.3748097239,
    "conference":"Big Ten",
    "abbreviation":"OSU",
    "season":2019,
    "week":17,
    "as_of":"2026-06-21T03:41:18Z"
  },
  {
    "school":"Georgia",
    "record":0.7461538462,
    "schedule":1658.8785446457,
    "results":1.5962228788,
    "elite_wins":12.5412234275,
    "playoff_raw":0.0,
    "record_z":1.5472010416,
    "schedule_z":1.7340429554,
    "results_z":1.4338413796,
    "elite_wins_z":3.6525999337,
    "playoff_z":0.0,
    "wins":11,
    "losses":2,
    "poll_score":1.6392476428,
    "poll_rating":1762.2796228508,
    "rank":3,
    "solver_rating":1906.2806238303,
    "conference":"SEC",
    "abbreviation":"UGA",
    "season":2019,
    "week":17,
    "as_of":"2026-06-21T03:41:18Z"
  },
  {
    "school":"Auburn",
    "record":0.45,
    "schedule":1731.5563171048,
    "results":2.0704909435,
    "elite_wins":6.9719620156,
    "playoff_raw":0.0,
    "record_z":0.7723310035,
    "schedule_z":2.6371647084,
    "results_z":1.9889658182,
    "elite_wins_z":1.8299227071,
    "playoff_z":0.0,
    "wins":8,
    "losses":4,
    "poll_score":1.5145232721,
    "poll_rating":1742.3237235353,
    "rank":4,
    "solver_rating":1819.1824254567,
    "conference":"SEC",
    "abbreviation":"AUB",
    "season":2019,
    "week":17,
    "as_of":"2026-06-21T03:41:18Z"
  },
  {
    "school":"Wisconsin",
    "record":0.5285714286,
    "schedule":1643.3996780934,
    "results":2.1330954582,
    "elite_wins":6.377473791,
    "playoff_raw":0.0,
    "record_z":0.9779087687,
    "schedule_z":1.5416966489,
    "results_z":2.0622435669,
    "elite_wins_z":1.6353618725,
    "playoff_z":0.0,
    "wins":10,
    "losses":4,
    "poll_score":1.3173186608,
    "poll_rating":1710.7709857303,
    "rank":5,
    "solver_rating":1885.0849273508,
    "conference":"Big Ten",
    "abbreviation":"WIS",
    "season":2019,
    "week":17,
    "as_of":"2026-06-21T03:41:18Z"
  },
  {
    "school":"Clemson",
    "record":0.8821428571,
    "schedule":1571.3621814969,
    "results":1.8051060955,
    "elite_wins":7.3196676495,
    "playoff_raw":0.0,
    "record_z":1.9030087122,
    "schedule_z":0.6465312083,
    "results_z":1.6783363963,
    "elite_wins_z":1.9437178935,
    "playoff_z":0.0,
    "wins":13,
    "losses":1,
    "poll_score":1.3119403712,
    "poll_rating":1709.9104593906,
    "rank":6,
    "solver_rating":2123.5796908001,
    "conference":"ACC",
    "abbreviation":"CLEM",
    "season":2019,
    "week":17,
    "as_of":"2026-06-21T03:41:18Z"
  },
  {
    "school":"Penn State",
    "record":0.725,
    "schedule":1595.7305462683,
    "results":1.5204645702,
    "elite_wins":5.9915442577,
    "playoff_raw":0.0,
    "record_z":1.4918531818,
    "schedule_z":0.9493418141,
    "results_z":1.3451672907,
    "elite_wins_z":1.5090569786,
    "playoff_z":0.0,
    "wins":10,
    "losses":2,
    "poll_score":1.1308451531,
    "poll_rating":1680.9352245019,
    "rank":7,
    "solver_rating":1836.0257537396,
    "conference":"Big Ten",
    "abbreviation":"PSU",
    "season":2019,
    "week":17,
    "as_of":"2026-06-21T03:41:18Z"
  },
  {
    "school":"Oklahoma",
    "record":0.7461538462,
    "schedule":1600.8250626361,
    "results":1.4997989967,
    "elite_wins":5.4023580181,
    "playoff_raw":0.0,
    "record_z":1.5472010416,
    "schedule_z":1.0126482199,
    "results_z":1.3209785128,
    "elite_wins_z":1.3162313485,
    "playoff_z":0.0,
    "wins":11,
    "losses":2,
    "poll_score":1.126362111,
    "poll_rating":1680.2179377673,
    "rank":8,
    "solver_rating":1756.1915358242,
    "conference":"Big 12",
    "abbreviation":"OU",
    "season":2019,
    "week":17,
    "as_of":"2026-06-21T03:41:18Z"
  },
  {
    "school":"Alabama",
    "record":0.725,
    "schedule":1593.4122151288,
    "results":1.8130048206,
    "elite_wins":4.1751002096,
    "playoff_raw":0.0,
    "record_z":1.4918531818,
    "schedule_z":0.9205333461,
    "results_z":1.6875817486,
    "elite_wins_z":0.9145811667,
    "playoff_z":0.0,
    "wins":10,
    "losses":2,
    "poll_score":1.1234601464,
    "poll_rating":1679.7536234224,
    "rank":9,
    "solver_rating":2005.5932450777,
    "conference":"SEC",
    "abbreviation":"ALA",
    "season":2019,
    "week":17,
    "as_of":"2026-06-21T03:41:18Z"
  },
  {
    "school":"Oregon",
    "record":0.7461538462,
    "schedule":1561.0021337466,
    "results":1.6843008977,
    "elite_wins":6.4949311515,
    "playoff_raw":0.0,
    "record_z":1.5472010416,
    "schedule_z":0.5177932989,
    "results_z":1.536935525,
    "elite_wins_z":1.673802671,
    "playoff_z":0.0,
    "wins":11,
    "losses":2,
    "poll_score":1.1193836965,
    "poll_rating":1679.1013914421,
    "rank":10,
    "solver_rating":1846.2203048012,
    "conference":"Pac-12",
    "abbreviation":"ORE",
    "season":2019,
    "week":17,
    "as_of":"2026-06-21T03:41:18Z"
  },
  {
    "school":"Michigan",
    "record":0.4923076923,
    "schedule":1633.5741414248,
    "results":1.7611858685,
    "elite_wins":5.1441267005,
    "playoff_raw":0.0,
    "record_z":0.8830267232,
    "schedule_z":1.4196007783,
    "results_z":1.6269283569,
    "elite_wins_z":1.231718824,
    "playoff_z":0.0,
    "wins":9,
    "losses":4,
    "poll_score":1.1048025603,
    "poll_rating":1676.7684096419,
    "rank":11,
    "solver_rating":1808.3156609267,
    "conference":"Big Ten",
    "abbreviation":"MICH",
    "season":2019,
    "week":17,
    "as_of":"2026-06-21T03:41:18Z"
  },
  {
    "school":"Florida",
    "record":0.7,
    "schedule":1657.5613957853,
    "results":1.23416524,
    "elite_wins":3.8345148805,
    "playoff_raw":0.0,
    "record_z":1.4264420746,
    "schedule_z":1.7176755607,
    "results_z":1.0100577466,
    "elite_wins_z":0.8031162745,
    "playoff_z":0.0,
    "wins":9,
    "losses":2,
    "poll_score":1.1036137004,
    "poll_rating":1676.5781920561,
    "rank":12,
    "solver_rating":1878.904802139,
    "conference":"SEC",
    "abbreviation":"FLA",
    "season":2019,
    "week":17,
    "as_of":"2026-06-21T03:41:18Z"
  },
  {
    "school":"Minnesota",
    "record":0.725,
    "schedule":1535.1103773421,
    "results":1.7154671404,
    "elite_wins":4.4379082628,
    "playoff_raw":0.0,
    "record_z":1.4918531818,
    "schedule_z":0.1960524469,
    "results_z":1.573415196,
    "elite_wins_z":1.0005915401,
    "playoff_z":0.0,
    "wins":10,
    "losses":2,
    "poll_score":0.9487158282,
    "poll_rating":1651.7945325155,
    "rank":13,
    "solver_rating":1745.0467677533,
    "conference":"Big Ten",
    "abbreviation":"MINN",
    "season":2019,
    "week":17,
    "as_of":"2026-06-21T03:41:18Z"
  },
  {
    "school":"Memphis",
    "record":0.7461538462,
    "schedule":1554.5213132267,
    "results":1.0688565551,
    "elite_wins":4.7315302324,
    "playoff_raw":0.0,
    "record_z":1.5472010416,
    "schedule_z":0.4372601483,
    "results_z":0.8165661377,
    "elite_wins_z":1.0966865224,
    "playoff_z":0.0,
    "wins":11,
    "losses":2,
    "poll_score":0.8479814896,
    "poll_rating":1635.6770383439,
    "rank":14,
    "solver_rating":1765.5837567153,
    "conference":"American Athletic",
    "abbreviation":"MEM",
    "season":2019,
    "week":17,
    "as_of":"2026-06-21T03:41:18Z"
  },
  {
    "school":"Iowa",
    "record":0.6192307692,
    "schedule":1561.354973693,
    "results":1.655083883,
    "elite_wins":1.6458280127,
    "playoff_raw":0.0,
    "record_z":1.2151138824,
    "schedule_z":0.5221778228,
    "results_z":1.5027373993,
    "elite_wins_z":0.086814881,
    "playoff_z":0.0,
    "wins":10,
    "losses":3,
    "poll_score":0.8036197896,
    "poll_rating":1628.5791663364,
    "rank":15,
    "solver_rating":1765.8905207322,
    "conference":"Big Ten",
    "abbreviation":"IOWA",
    "season":2019,
    "week":17,
    "as_of":"2026-06-21T03:41:18Z"
  },
  {
    "school":"Texas A&M",
    "record":0.3125,
    "schedule":1669.7654195839,
    "results":1.4342714047,
    "elite_wins":0.0,
    "playoff_raw":0.0,
    "record_z":0.4125699143,
    "schedule_z":1.8693274206,
    "results_z":1.2442793411,
    "elite_wins_z":-0.4518226538,
    "playoff_z":0.0,
    "wins":7,
    "losses":5,
    "poll_score":0.7538920806,
    "poll_rating":1620.6227328921,
    "rank":16,
    "solver_rating":1685.9860868977,
    "conference":"SEC",
    "abbreviation":"TA&M",
    "season":2019,
    "week":17,
    "as_of":"2026-06-21T03:41:18Z"
  },
  {
    "school":"Baylor",
    "record":0.6192307692,
    "schedule":1558.4847341021,
    "results":1.3625065653,
    "elite_wins":2.0432703576,
    "playoff_raw":0.0,
    "record_z":1.2151138824,
    "schedule_z":0.4865111296,
    "results_z":1.1602795546,
    "elite_wins_z":0.2168876244,
    "playoff_z":0.0,
    "wins":10,
    "losses":3,
    "poll_score":0.7317934185,
    "poll_rating":1617.0869469554,
    "rank":17,
    "solver_rating":1761.8698699814,
    "conference":"Big 12",
    "abbreviation":"BAY",
    "season":2019,
    "week":17,
    "as_of":"2026-06-21T03:41:18Z"
  },
  {
    "school":"Texas",
    "record":0.3653846154,
    "schedule":1603.9601948529,
    "results":1.2309109844,
    "elite_wins":2.3203648223,
    "playoff_raw":0.0,
    "record_z":0.550939564,
    "schedule_z":1.05160657,
    "results_z":1.0062486838,
    "elite_wins_z":0.307573576,
    "playoff_z":0.0,
    "wins":8,
    "losses":5,
    "poll_score":0.6591577168,
    "poll_rating":1605.4652346848,
    "rank":18,
    "solver_rating":1762.9232572141,
    "conference":"Big 12",
    "abbreviation":"TEX",
    "season":2019,
    "week":17,
    "as_of":"2026-06-21T03:41:18Z"
  },
  {
    "school":"Notre Dame",
    "record":0.7461538462,
    "schedule":1517.0326244702,
    "results":1.0982894968,
    "elite_wins":2.4803801166,
    "playoff_raw":0.0,
    "record_z":1.5472010416,
    "schedule_z":-0.0285886134,
    "results_z":0.851017003,
    "elite_wins_z":0.3599425009,
    "playoff_z":0.0,
    "wins":11,
    "losses":2,
    "poll_score":0.6506188067,
    "poll_rating":1604.0990090754,
    "rank":19,
    "solver_rating":1883.4554656414,
    "conference":"FBS Independents",
    "abbreviation":"ND",
    "season":2019,
    "week":17,
    "as_of":"2026-06-21T03:41:18Z"
  },
  {
    "school":"Utah",
    "record":0.6192307692,
    "schedule":1535.5542839671,
    "results":1.1122865186,
    "elite_wins":1.9392141047,
    "playoff_raw":0.0,
    "record_z":1.2151138824,
    "schedule_z":0.2015686001,
    "results_z":0.8674003302,
    "elite_wins_z":0.1828326666,
    "playoff_z":0.0,
    "wins":10,
    "losses":3,
    "poll_score":0.594047354,
    "poll_rating":1595.0475766428,
    "rank":20,
    "solver_rating":1743.2583715644,
    "conference":"Pac-12",
    "abbreviation":"UTAH",
    "season":2019,
    "week":17,
    "as_of":"2026-06-21T03:41:18Z"
  },
  {
    "school":"Navy",
    "record":0.725,
    "schedule":1527.6333583197,
    "results":0.8845848555,
    "elite_wins":1.7380768572,
    "playoff_raw":0.0,
    "record_z":1.4918531818,
    "schedule_z":0.1031401534,
    "results_z":0.6008785732,
    "elite_wins_z":0.1170055751,
    "playoff_z":0.0,
    "wins":10,
    "losses":2,
    "poll_score":0.5711642991,
    "poll_rating":1591.3862878537,
    "rank":21,
    "solver_rating":1750.5751043738,
    "conference":"American Athletic",
    "abbreviation":"NAVY",
    "season":2019,
    "week":17,
    "as_of":"2026-06-21T03:41:18Z"
  },
  {
    "school":"USC",
    "record":0.3653846154,
    "schedule":1571.3308020036,
    "results":0.9858556949,
    "elite_wins":1.7203648223,
    "playoff_raw":0.0,
    "record_z":0.550939564,
    "schedule_z":0.6461412747,
    "results_z":0.7194147388,
    "elite_wins_z":0.1112088778,
    "playoff_z":0.0,
    "wins":8,
    "losses":5,
    "poll_score":0.4736241473,
    "poll_rating":1575.7798635652,
    "rank":22,
    "solver_rating":1572.6532585134,
    "conference":"Pac-12",
    "abbreviation":"USC",
    "season":2019,
    "week":17,
    "as_of":"2026-06-21T03:41:18Z"
  },
  {
    "school":"Tennessee",
    "record":0.3125,
    "schedule":1605.6313626547,
    "results":0.6828627245,
    "elite_wins":1.4110532928,
    "playoff_raw":0.0,
    "record_z":0.4125699143,
    "schedule_z":1.0723731392,
    "results_z":0.3647655116,
    "elite_wins_z":0.0099791026,
    "playoff_z":0.0,
    "wins":7,
    "losses":5,
    "poll_score":0.4321310655,
    "poll_rating":1569.1409704812,
    "rank":23,
    "solver_rating":1626.5382313285,
    "conference":"SEC",
    "abbreviation":"TENN",
    "season":2019,
    "week":17,
    "as_of":"2026-06-21T03:41:18Z"
  },
  {
    "school":"Oklahoma State",
    "record":0.3125,
    "schedule":1576.9397410727,
    "results":1.1764084854,
    "elite_wins":0.0,
    "playoff_raw":0.0,
    "record_z":0.4125699143,
    "schedule_z":0.7158400934,
    "results_z":0.9424542363,
    "elite_wins_z":-0.4518226538,
    "playoff_z":0.0,
    "wins":7,
    "losses":5,
    "poll_score":0.4276868434,
    "poll_rating":1568.4298949518,
    "rank":24,
    "solver_rating":1572.7507215462,
    "conference":"Big 12",
    "abbreviation":"OKST",
    "season":2019,
    "week":17,
    "as_of":"2026-06-21T03:41:18Z"
  },
  {
    "school":"Boise State",
    "record":0.7461538462,
    "schedule":1502.648492821,
    "results":0.492609294,
    "elite_wins":1.7952197143,
    "playoff_raw":0.0,
    "record_z":1.5472010416,
    "schedule_z":-0.2073313259,
    "results_z":0.142076411,
    "elite_wins_z":0.135706975,
    "playoff_z":0.0,
    "wins":11,
    "losses":2,
    "poll_score":0.4097566943,
    "poll_rating":1565.5610710806,
    "rank":25,
    "solver_rating":1675.146741938,
    "conference":"Mountain West",
    "abbreviation":"BOIS",
    "season":2019,
    "week":17,
    "as_of":"2026-06-21T03:41:18Z"
  },
  {
    "school":"Virginia",
    "record":0.3653846154,
    "schedule":1572.5459263175,
    "results":0.741537814,
    "elite_wins":1.6924120456,
    "playoff_raw":0.0,
    "record_z":0.550939564,
    "schedule_z":0.6612408734,
    "results_z":0.4334439207,
    "elite_wins_z":0.1020606469,
    "playoff_z":0.0,
    "wins":8,
    "losses":5,
    "poll_score":0.4070323103,
    "poll_rating":1565.1251696523,
    "rank":26,
    "solver_rating":1618.3884508572,
    "conference":"ACC",
    "abbreviation":"UVA",
    "season":2019,
    "week":17,
    "as_of":"2026-06-21T03:41:18Z"
  },
  {
    "school":"Kansas State",
    "record":0.3125,
    "schedule":1534.2138099564,
    "results":1.2108096768,
    "elite_wins":1.8011970989,
    "playoff_raw":0.0,
    "record_z":0.4125699143,
    "schedule_z":0.1849113582,
    "results_z":0.9827203717,
    "elite_wins_z":0.1376632205,
    "playoff_z":0.0,
    "wins":7,
    "losses":5,
    "poll_score":0.4030744166,
    "poll_rating":1564.4919066549,
    "rank":27,
    "solver_rating":1629.0281273984,
    "conference":"Big 12",
    "abbreviation":"KSU",
    "season":2019,
    "week":17,
    "as_of":"2026-06-21T03:41:18Z"
  },
  {
    "school":"App State",
    "record":0.8730769231,
    "schedule":1459.5972644139,
    "results":0.0165470024,
    "elite_wins":5.1047480957,
    "playoff_raw":0.0,
    "record_z":1.8792882008,
    "schedule_z":-0.7423023295,
    "results_z":-0.4151481462,
    "elite_wins_z":1.2188312109,
    "playoff_z":0.0,
    "wins":12,
    "losses":1,
    "poll_score":0.3963092342,
    "poll_rating":1563.4094774661,
    "rank":28,
    "solver_rating":1793.581091916,
    "conference":"Sun Belt",
    "abbreviation":"APP",
    "season":2019,
    "week":17,
    "as_of":"2026-06-21T03:41:18Z"
  },
  {
    "school":"Cincinnati",
    "record":0.6464285714,
    "schedule":1509.9106540261,
    "results":0.5180363137,
    "elite_wins":1.8273958431,
    "playoff_raw":0.0,
    "record_z":1.2862754165,
    "schedule_z":-0.1170889377,
    "results_z":0.1718383981,
    "elite_wins_z":0.1462374013,
    "playoff_z":0.0,
    "wins":11,
    "losses":3,
    "poll_score":0.3703864937,
    "poll_rating":1559.261838998,
    "rank":29,
    "solver_rating":1691.5205806888,
    "conference":"American Athletic",
    "abbreviation":"CIN",
    "season":2019,
    "week":17,
    "as_of":"2026-06-21T03:41:18Z"
  },
  {
    "school":"Washington",
    "record":0.3125,
    "schedule":1545.1306149806,
    "results":1.2104696599,
    "elite_wins":0.0,
    "playoff_raw":0.0,
    "record_z":0.4125699143,
    "schedule_z":0.3205677461,
    "results_z":0.9823223864,
    "elite_wins_z":-0.4518226538,
    "playoff_z":0.0,
    "wins":7,
    "losses":5,
    "poll_score":0.3502952831,
    "poll_rating":1556.04724529,
    "rank":30,
    "solver_rating":1787.4171138899,
    "conference":"Pac-12",
    "abbreviation":"WASH",
    "season":2019,
    "week":17,
    "as_of":"2026-06-21T03:41:18Z"
  },
  {
    "school":"Air Force",
    "record":0.725,
    "schedule":1490.8231147051,
    "results":0.6676691035,
    "elite_wins":0.0,
    "playoff_raw":0.0,
    "record_z":1.4918531818,
    "schedule_z":-0.35427799,
    "results_z":0.3469815811,
    "elite_wins_z":-0.4518226538,
    "playoff_z":0.0,
    "wins":10,
    "losses":2,
    "poll_score":0.3299610774,
    "poll_rating":1552.79377238,
    "rank":31,
    "solver_rating":1736.9494400092,
    "conference":"Mountain West",
    "abbreviation":"AF",
    "season":2019,
    "week":17,
    "as_of":"2026-06-21T03:41:18Z"
  },
  {
    "school":"California",
    "record":0.3125,
    "schedule":1553.1384614532,
    "results":0.6420629464,
    "elite_wins":1.8249283904,
    "playoff_raw":0.0,
    "record_z":0.4125699143,
    "schedule_z":0.4200763042,
    "results_z":0.3170099161,
    "elite_wins_z":0.145429867,
    "playoff_z":0.0,
    "wins":7,
    "losses":5,
    "poll_score":0.2961275259,
    "poll_rating":1547.3804041404,
    "rank":32,
    "solver_rating":1508.2785728677,
    "conference":"Pac-12",
    "abbreviation":"CAL",
    "season":2019,
    "week":17,
    "as_of":"2026-06-21T03:41:18Z"
  },
  {
    "school":"SMU",
    "record":0.6192307692,
    "schedule":1501.850243837,
    "results":0.5833697842,
    "elite_wins":0.0,
    "playoff_raw":0.0,
    "record_z":1.2151138824,
    "schedule_z":-0.2172506726,
    "results_z":0.2483103532,
    "elite_wins_z":-0.4518226538,
    "playoff_z":0.0,
    "wins":10,
    "losses":3,
    "poll_score":0.2644737747,
    "poll_rating":1542.3158039469,
    "rank":33,
    "solver_rating":1628.3829089584,
    "conference":"American Athletic",
    "abbreviation":"SMU",
    "season":2019,
    "week":17,
    "as_of":"2026-06-21T03:41:18Z"
  },
  {
    "school":"Arizona State",
    "record":0.3125,
    "schedule":1517.9762816954,
    "results":0.7650446184,
    "elite_wins":2.2495911907,
    "playoff_raw":0.0,
    "record_z":0.4125699143,
    "schedule_z":-0.0168623684,
    "results_z":0.4609583214,
    "elite_wins_z":0.2844111713,
    "playoff_z":0.0,
    "wins":7,
    "losses":5,
    "poll_score":0.2540060178,
    "poll_rating":1540.6409628467,
    "rank":34,
    "solver_rating":1532.5205933356,
    "conference":"Pac-12",
    "abbreviation":"ASU",
    "season":2019,
    "week":17,
    "as_of":"2026-06-21T03:41:18Z"
  },
  {
    "school":"Michigan State",
    "record":0.2384615385,
    "schedule":1570.4100065745,
    "results":0.7567490958,
    "elite_wins":0.0,
    "playoff_raw":0.0,
    "record_z":0.2188524048,
    "schedule_z":0.6346991191,
    "results_z":0.4512485229,
    "elite_wins_z":-0.4518226538,
    "playoff_z":0.0,
    "wins":7,
    "losses":6,
    "poll_score":0.2415799054,
    "poll_rating":1538.6527848638,
    "rank":35,
    "solver_rating":1466.6397274799,
    "conference":"Big Ten",
    "abbreviation":"MSU",
    "season":2019,
    "week":17,
    "as_of":"2026-06-21T03:41:18Z"
  },
  {
    "school":"Louisville",
    "record":0.3125,
    "schedule":1578.2786602585,
    "results":0.4914691643,
    "elite_wins":0.0,
    "playoff_raw":0.0,
    "record_z":0.4125699143,
    "schedule_z":0.7324780144,
    "results_z":0.1407419045,
    "elite_wins_z":-0.4518226538,
    "playoff_z":0.0,
    "wins":7,
    "losses":5,
    "poll_score":0.2389362264,
    "poll_rating":1538.2297962292,
    "rank":36,
    "solver_rating":1511.4691646659,
    "conference":"ACC",
    "abbreviation":"LOU",
    "season":2019,
    "week":17,
    "as_of":"2026-06-21T03:41:18Z"
  },
  {
    "school":"Florida Atlantic",
    "record":0.6192307692,
    "schedule":1517.7454632867,
    "results":0.2534678366,
    "elite_wins":0.0,
    "playoff_raw":0.0,
    "record_z":1.2151138824,
    "schedule_z":-0.0197306061,
    "results_z":-0.1378354725,
    "elite_wins_z":-0.4518226538,
    "playoff_z":0.0,
    "wins":10,
    "losses":3,
    "poll_score":0.2152531912,
    "poll_rating":1534.4405105849,
    "rank":37,
    "solver_rating":1827.6527908387,
    "conference":"Conference USA",
    "abbreviation":"FAU",
    "season":2019,
    "week":17,
    "as_of":"2026-06-21T03:41:18Z"
  },
  {
    "school":"UCF",
    "record":0.5875,
    "schedule":1451.8607903916,
    "results":0.4138649468,
    "elite_wins":3.0192585142,
    "playoff_raw":0.0,
    "record_z":1.1320920926,
    "schedule_z":-0.8384387099,
    "results_z":0.0499072038,
    "elite_wins_z":0.5363036573,
    "playoff_z":0.0,
    "wins":9,
    "losses":3,
    "poll_score":0.1969476688,
    "poll_rating":1531.5116270145,
    "rank":38,
    "solver_rating":1778.6690491738,
    "conference":"American Athletic",
    "abbreviation":"UCF",
    "season":2019,
    "week":17,
    "as_of":"2026-06-21T03:41:18Z"
  },
  {
    "school":"Indiana",
    "record":0.3125,
    "schedule":1512.405558909,
    "results":0.9367949387,
    "elite_wins":0.0,
    "playoff_raw":0.0,
    "record_z":0.4125699143,
    "schedule_z":-0.0860862969,
    "results_z":0.6619897785,
    "elite_wins_z":-0.4518226538,
    "playoff_z":0.0,
    "wins":7,
    "losses":5,
    "poll_score":0.1839515677,
    "poll_rating":1529.4322508328,
    "rank":39,
    "solver_rating":1577.4694782726,
    "conference":"Big Ten",
    "abbreviation":"IU",
    "season":2019,
    "week":17,
    "as_of":"2026-06-21T03:41:18Z"
  },
  {
    "school":"Kentucky",
    "record":0.3125,
    "schedule":1535.6849909888,
    "results":0.7025727044,
    "elite_wins":0.0,
    "playoff_raw":0.0,
    "record_z":0.4125699143,
    "schedule_z":0.2031928155,
    "results_z":0.38783578,
    "elite_wins_z":-0.4518226538,
    "playoff_z":0.0,
    "wins":7,
    "losses":5,
    "poll_score":0.1817960128,
    "poll_rating":1529.0873620469,
    "rank":40,
    "solver_rating":1707.4828125692,
    "conference":"SEC",
    "abbreviation":"UK",
    "season":2019,
    "week":17,
    "as_of":"2026-06-21T03:41:18Z"
  },
  {
    "school":"Pittsburgh",
    "record":0.3125,
    "schedule":1540.2866774923,
    "results":0.0276924619,
    "elite_wins":3.4626650315,
    "playoff_raw":0.0,
    "record_z":0.4125699143,
    "schedule_z":0.2603751291,
    "results_z":-0.4021025347,
    "elite_wins_z":0.6814193022,
    "playoff_z":0.0,
    "wins":7,
    "losses":5,
    "poll_score":0.1634448001,
    "poll_rating":1526.1511680198,
    "rank":41,
    "solver_rating":1452.4553990585,
    "conference":"ACC",
    "abbreviation":"PITT",
    "season":2019,
    "week":17,
    "as_of":"2026-06-21T03:41:18Z"
  },
  {
    "school":"Wake Forest",
    "record":0.3125,
    "schedule":1512.4021582446,
    "results":0.3444679674,
    "elite_wins":1.663840617,
    "playoff_raw":0.0,
    "record_z":0.4125699143,
    "schedule_z":-0.0861285549,
    "results_z":-0.0313210342,
    "elite_wins_z":0.092709947,
    "playoff_z":0.0,
    "wins":7,
    "losses":5,
    "poll_score":0.09378224,
    "poll_rating":1515.0051584028,
    "rank":42,
    "solver_rating":1451.1324035032,
    "conference":"ACC",
    "abbreviation":"WAKE",
    "season":2019,
    "week":17,
    "as_of":"2026-06-21T03:41:18Z"
  },
  {
    "school":"Marshall",
    "record":0.3125,
    "schedule":1539.9148141392,
    "results":-0.1854114474,
    "elite_wins":2.1906870856,
    "playoff_raw":0.0,
    "record_z":0.4125699143,
    "schedule_z":0.2557542131,
    "results_z":-0.6515378157,
    "elite_wins_z":0.2651333599,
    "playoff_z":0.0,
    "wins":7,
    "losses":5,
    "poll_score":0.0442836992,
    "poll_rating":1507.0853918769,
    "rank":43,
    "solver_rating":1487.4550856489,
    "conference":"Conference USA",
    "abbreviation":"MRSH",
    "season":2019,
    "week":17,
    "as_of":"2026-06-21T03:41:18Z"
  },
  {
    "school":"Virginia Tech",
    "record":0.25,
    "schedule":1496.9015260285,
    "results":0.4876396931,
    "elite_wins":1.5495549028,
    "playoff_raw":0.0,
    "record_z":0.2490421465,
    "schedule_z":-0.2787453298,
    "results_z":0.1362595594,
    "elite_wins_z":0.0553071474,
    "playoff_z":0.0,
    "wins":6,
    "losses":5,
    "poll_score":0.0438722804,
    "poll_rating":1507.019564869,
    "rank":44,
    "solver_rating":1661.4987398276,
    "conference":"ACC",
    "abbreviation":"VT",
    "season":2019,
    "week":17,
    "as_of":"2026-06-21T03:41:18Z"
  },
  {
    "school":"Louisiana",
    "record":0.6192307692,
    "schedule":1474.1662474924,
    "results":-0.0964029483,
    "elite_wins":0.0,
    "playoff_raw":0.0,
    "record_z":1.2151138824,
    "schedule_z":-0.5612625825,
    "results_z":-0.5473545558,
    "elite_wins_z":-0.4518226538,
    "playoff_z":0.0,
    "wins":10,
    "losses":3,
    "poll_score":-0.0021684236,
    "poll_rating":1499.6530522166,
    "rank":45,
    "solver_rating":1743.2725982891,
    "conference":"Sun Belt",
    "abbreviation":"UL",
    "season":2019,
    "week":17,
    "as_of":"2026-06-21T03:41:18Z"
  },
  {
    "school":"Hawai'i",
    "record":0.4107142857,
    "schedule":1508.328596786,
    "results":0.066391858,
    "elite_wins":0.0,
    "playoff_raw":0.0,
    "record_z":0.6695421209,
    "schedule_z":-0.1367481851,
    "results_z":-0.3568054082,
    "elite_wins_z":-0.4518226538,
    "playoff_z":0.0,
    "wins":9,
    "losses":5,
    "poll_score":-0.0048921188,
    "poll_rating":1499.2172609922,
    "rank":46,
    "solver_rating":1542.2297772923,
    "conference":"Mountain West",
    "abbreviation":"HAW",
    "season":2019,
    "week":17,
    "as_of":"2026-06-21T03:41:18Z"
  },
  {
    "school":"Temple",
    "record":0.3125,
    "schedule":1485.3966324408,
    "results":0.0626361058,
    "elite_wins":1.7170413366,
    "playoff_raw":0.0,
    "record_z":0.4125699143,
    "schedule_z":-0.4217095307,
    "results_z":-0.361201466,
    "elite_wins_z":0.1101211857,
    "playoff_z":0.0,
    "wins":7,
    "losses":5,
    "poll_score":-0.0567793049,
    "poll_rating":1490.9153112192,
    "rank":47,
    "solver_rating":1400.6033047544,
    "conference":"American Athletic",
    "abbreviation":"TEM",
    "season":2019,
    "week":17,
    "as_of":"2026-06-21T03:41:18Z"
  },
  {
    "school":"Western Kentucky",
    "record":0.5875,
    "schedule":1453.8259430993,
    "results":-0.0163845397,
    "elite_wins":0.0,
    "playoff_raw":0.0,
    "record_z":1.1320920926,
    "schedule_z":-0.814018972,
    "results_z":-0.4536940767,
    "elite_wins_z":-0.4518226538,
    "playoff_z":0.0,
    "wins":9,
    "losses":3,
    "poll_score":-0.0568819797,
    "poll_rating":1490.8988832502,
    "rank":48,
    "solver_rating":1597.9677109355,
    "conference":"Conference USA",
    "abbreviation":"WKU",
    "season":2019,
    "week":17,
    "as_of":"2026-06-21T03:41:18Z"
  },
  {
    "school":"South Carolina",
    "record":-0.2,
    "schedule":1756.0692691988,
    "results":1.1295448978,
    "elite_wins":4.4074500489,
    "playoff_raw":0.0,
    "record_z":-0.9283577816,
    "schedule_z":2.9417720115,
    "results_z":0.8876010326,
    "elite_wins_z":0.9906233435,
    "playoff_z":0.0,
    "wins":3,
    "losses":8,
    "poll_score":-0.0924716648,
    "poll_rating":1485.204533637,
    "rank":49,
    "solver_rating":1517.4016299006,
    "conference":"SEC",
    "abbreviation":"SC",
    "season":2019,
    "week":17,
    "as_of":"2026-06-21T03:41:18Z"
  },
  {
    "school":"Mississippi State",
    "record":0.0375,
    "schedule":1692.5196451998,
    "results":1.1061426791,
    "elite_wins":3.5315070321,
    "playoff_raw":0.0,
    "record_z":-0.306952264,
    "schedule_z":2.1520801169,
    "results_z":0.860209048,
    "elite_wins_z":0.7039495333,
    "playoff_z":0.0,
    "wins":5,
    "losses":7,
    "poll_score":-0.1513468567,
    "poll_rating":1475.7845029249,
    "rank":50,
    "solver_rating":1542.2826423435,
    "conference":"SEC",
    "abbreviation":"MSST",
    "season":2019,
    "week":17,
    "as_of":"2026-06-21T03:41:18Z"
  },
  {
    "school":"San Diego State",
    "record":0.5875,
    "schedule":1417.7020107955,
    "results":-0.0982792184,
    "elite_wins":0.0,
    "playoff_raw":0.0,
    "record_z":1.1320920926,
    "schedule_z":-1.2629087489,
    "results_z":-0.5495507049,
    "elite_wins_z":-0.4518226538,
    "playoff_z":0.0,
    "wins":9,
    "losses":3,
    "poll_score":-0.1786433214,
    "poll_rating":1471.4170685789,
    "rank":51,
    "solver_rating":1657.8379221912,
    "conference":"Mountain West",
    "abbreviation":"SDSU",
    "season":2019,
    "week":17,
    "as_of":"2026-06-21T03:41:18Z"
  },
  {
    "school":"Wyoming",
    "record":0.3125,
    "schedule":1446.2105861118,
    "results":0.1392770406,
    "elite_wins":0.0,
    "playoff_raw":0.0,
    "record_z":0.4125699143,
    "schedule_z":-0.9086503058,
    "results_z":-0.2714942749,
    "elite_wins_z":-0.4518226538,
    "playoff_z":0.0,
    "wins":7,
    "losses":5,
    "poll_score":-0.2210486871,
    "poll_rating":1464.6322100697,
    "rank":52,
    "solver_rating":1596.3833575753,
    "conference":"Mountain West",
    "abbreviation":"WYO",
    "season":2019,
    "week":17,
    "as_of":"2026-06-21T03:41:18Z"
  },
  {
    "school":"Miami (OH)",
    "record":0.2384615385,
    "schedule":1514.9866617662,
    "results":-0.3604057258,
    "elite_wins":0.0,
    "playoff_raw":0.0,
    "record_z":0.2188524048,
    "schedule_z":-0.0540125272,
    "results_z":-0.8563662825,
    "elite_wins_z":-0.4518226538,
    "playoff_z":0.0,
    "wins":7,
    "losses":6,
    "poll_score":-0.2237642101,
    "poll_rating":1464.197726386,
    "rank":53,
    "solver_rating":1442.6526199742,
    "conference":"Mid-American",
    "abbreviation":"M-OH",
    "season":2019,
    "week":17,
    "as_of":"2026-06-21T03:41:18Z"
  },
  {
    "school":"Iowa State",
    "record":0.175,
    "schedule":1600.9695195764,
    "results":1.3284951966,
    "elite_wins":1.7004132147,
    "playoff_raw":0.0,
    "record_z":0.0528088252,
    "schedule_z":1.014443297,
    "results_z":1.1204697016,
    "elite_wins_z":0.1046792255,
    "playoff_z":0.0,
    "wins":6,
    "losses":6,
    "poll_score":-0.3295243602,
    "poll_rating":1447.2761023712,
    "rank":54,
    "solver_rating":1592.8547788717,
    "conference":"Big 12",
    "abbreviation":"ISU",
    "season":2019,
    "week":17,
    "as_of":"2026-06-21T03:41:18Z"
  },
  {
    "school":"Arkansas State",
    "record":0.3125,
    "schedule":1448.4228552279,
    "results":-0.6691833618,
    "elite_wins":0.0,
    "playoff_raw":0.0,
    "record_z":0.4125699143,
    "schedule_z":-0.881159805,
    "results_z":-1.2177863836,
    "elite_wins_z":-0.4518226538,
    "playoff_z":0.0,
    "wins":7,
    "losses":5,
    "poll_score":-0.442110883,
    "poll_rating":1429.2622587225,
    "rank":55,
    "solver_rating":1450.2242538295,
    "conference":"Sun Belt",
    "abbreviation":"ARST",
    "season":2019,
    "week":17,
    "as_of":"2026-06-21T03:41:18Z"
  },
  {
    "school":"UAB",
    "record":0.3653846154,
    "schedule":1401.8143320742,
    "results":-0.4867670315,
    "elite_wins":0.0,
    "playoff_raw":0.0,
    "record_z":0.550939564,
    "schedule_z":-1.4603351115,
    "results_z":-1.0042705041,
    "elite_wins_z":-0.4518226538,
    "playoff_z":0.0,
    "wins":8,
    "losses":5,
    "poll_score":-0.4823095304,
    "poll_rating":1422.8304751345,
    "rank":56,
    "solver_rating":1419.348271698,
    "conference":"Conference USA",
    "abbreviation":"UAB",
    "season":2019,
    "week":17,
    "as_of":"2026-06-21T03:41:18Z"
  },
  {
    "school":"Central Michigan",
    "record":0.2384615385,
    "schedule":1394.6422556389,
    "results":-0.4427172246,
    "elite_wins":0.0,
    "playoff_raw":0.0,
    "record_z":0.2188524048,
    "schedule_z":-1.549458072,
    "results_z":-0.9527107932,
    "elite_wins_z":-0.4518226538,
    "playoff_z":0.0,
    "wins":7,
    "losses":6,
    "poll_score":-0.5758849125,
    "poll_rating":1407.8584140027,
    "rank":57,
    "solver_rating":1439.9531751102,
    "conference":"Mid-American",
    "abbreviation":"CMU",
    "season":2019,
    "week":17,
    "as_of":"2026-06-21T03:41:18Z"
  },
  {
    "school":"Nebraska",
    "record":0.0375,
    "schedule":1543.5085847917,
    "results":1.5318656209,
    "elite_wins":0.0,
    "playoff_raw":0.0,
    "record_z":-0.306952264,
    "schedule_z":0.3004117795,
    "results_z":1.3585120684,
    "elite_wins_z":-0.4518226538,
    "playoff_z":0.0,
    "wins":5,
    "losses":7,
    "poll_score":-0.6009292723,
    "poll_rating":1403.8513164394,
    "rank":58,
    "solver_rating":1570.3552996274,
    "conference":"Big Ten",
    "abbreviation":"NEB",
    "season":2019,
    "week":17,
    "as_of":"2026-06-21T03:41:18Z"
  },
  {
    "school":"Buffalo",
    "record":0.3125,
    "schedule":1379.3135119234,
    "results":-0.6267984265,
    "elite_wins":0.0,
    "playoff_raw":0.0,
    "record_z":0.4125699143,
    "schedule_z":-1.7399388947,
    "results_z":-1.1681753826,
    "elite_wins_z":-0.4518226538,
    "playoff_z":0.0,
    "wins":7,
    "losses":5,
    "poll_score":-0.6191356425,
    "poll_rating":1400.9382972021,
    "rank":59,
    "solver_rating":1648.7013689241,
    "conference":"Mid-American",
    "abbreviation":"BUF",
    "season":2019,
    "week":17,
    "as_of":"2026-06-21T03:41:18Z"
  },
  {
    "school":"Colorado",
    "record":0.0375,
    "schedule":1566.6325787608,
    "results":0.9131164997,
    "elite_wins":1.9677855332,
    "playoff_raw":0.0,
    "record_z":-0.306952264,
    "schedule_z":0.5877593586,
    "results_z":0.6342744818,
    "elite_wins_z":0.1921833665,
    "playoff_z":0.0,
    "wins":5,
    "losses":7,
    "poll_score":-0.6213689828,
    "poll_rating":1400.5809627549,
    "rank":60,
    "solver_rating":1359.4459033212,
    "conference":"Pac-12",
    "abbreviation":"COLO",
    "season":2019,
    "week":17,
    "as_of":"2026-06-21T03:41:18Z"
  },
  {
    "school":"Ole Miss",
    "record":-0.2,
    "schedule":1621.0436522467,
    "results":1.2740613811,
    "elite_wins":0.0,
    "playoff_raw":0.0,
    "record_z":-0.9283577816,
    "schedule_z":1.2638921349,
    "results_z":1.0567556471,
    "elite_wins_z":-0.4518226538,
    "playoff_z":0.0,
    "wins":3,
    "losses":8,
    "poll_score":-0.6229505698,
    "poll_rating":1400.3279088395,
    "rank":61,
    "solver_rating":1608.9624786786,
    "conference":"SEC",
    "abbreviation":"MISS",
    "season":2019,
    "week":17,
    "as_of":"2026-06-21T03:41:18Z"
  },
  {
    "school":"TCU",
    "record":-0.05,
    "schedule":1570.9199058999,
    "results":1.0513943818,
    "elite_wins":1.9289846433,
    "playoff_raw":0.0,
    "record_z":-0.5358911389,
    "schedule_z":0.6410353228,
    "results_z":0.7961268969,
    "elite_wins_z":0.1794848248,
    "playoff_z":0.0,
    "wins":4,
    "losses":7,
    "poll_score":-0.6321055944,
    "poll_rating":1398.8631049018,
    "rank":62,
    "solver_rating":1570.3398219908,
    "conference":"Big 12",
    "abbreviation":"TCU",
    "season":2019,
    "week":17,
    "as_of":"2026-06-21T03:41:18Z"
  },
  {
    "school":"Arkansas",
    "record":-0.5,
    "schedule":1687.8041203689,
    "results":1.2967602149,
    "elite_wins":0.0,
    "playoff_raw":0.0,
    "record_z":-1.713291067,
    "schedule_z":2.0934832047,
    "results_z":1.0833243292,
    "elite_wins_z":-0.4518226538,
    "playoff_z":0.0,
    "wins":1,
    "losses":10,
    "poll_score":-0.6381467049,
    "poll_rating":1397.8965272123,
    "rank":63,
    "solver_rating":1287.6096972993,
    "conference":"SEC",
    "abbreviation":"ARK",
    "season":2019,
    "week":17,
    "as_of":"2026-06-21T03:41:18Z"
  },
  {
    "school":"Missouri",
    "record":0.1,
    "schedule":1566.0885459538,
    "results":0.8943447687,
    "elite_wins":0.0,
    "playoff_raw":0.0,
    "record_z":-0.1434244962,
    "schedule_z":0.5809989992,
    "results_z":0.6123024213,
    "elite_wins_z":-0.4518226538,
    "playoff_z":0.0,
    "wins":5,
    "losses":6,
    "poll_score":-0.6757731796,
    "poll_rating":1391.876291262,
    "rank":64,
    "solver_rating":1540.3376574867,
    "conference":"SEC",
    "abbreviation":"MIZ",
    "season":2019,
    "week":17,
    "as_of":"2026-06-21T03:41:18Z"
  },
  {
    "school":"Stanford",
    "record":-0.1,
    "schedule":1572.9174142582,
    "results":0.9315365807,
    "elite_wins":2.0820712475,
    "playoff_raw":0.0,
    "record_z":-0.6667133531,
    "schedule_z":0.6658571244,
    "results_z":0.6558349407,
    "elite_wins_z":0.2295861662,
    "playoff_z":0.0,
    "wins":4,
    "losses":8,
    "poll_score":-0.6873144554,
    "poll_rating":1390.0296871348,
    "rank":65,
    "solver_rating":1358.1913112113,
    "conference":"Pac-12",
    "abbreviation":"STAN",
    "season":2019,
    "week":17,
    "as_of":"2026-06-21T03:41:18Z"
  },
  {
    "school":"Louisiana Tech",
    "record":0.5875,
    "schedule":1309.2363897149,
    "results":-0.8896357522,
    "elite_wins":0.0,
    "playoff_raw":0.0,
    "record_z":1.1320920926,
    "schedule_z":-2.6107439746,
    "results_z":-1.4758229637,
    "elite_wins_z":-0.4518226538,
    "playoff_z":0.0,
    "wins":9,
    "losses":3,
    "poll_score":-0.6974724132,
    "poll_rating":1388.4044138944,
    "rank":66,
    "solver_rating":1557.2869293246,
    "conference":"Conference USA",
    "abbreviation":"LT",
    "season":2019,
    "week":17,
    "as_of":"2026-06-21T03:41:18Z"
  },
  {
    "school":"Washington State",
    "record":0.0375,
    "schedule":1532.9227124806,
    "results":1.1646320528,
    "elite_wins":0.0,
    "playoff_raw":0.0,
    "record_z":-0.306952264,
    "schedule_z":0.1688676879,
    "results_z":0.9286700792,
    "elite_wins_z":-0.4518226538,
    "playoff_z":0.0,
    "wins":5,
    "losses":7,
    "poll_score":-0.7330310498,
    "poll_rating":1382.7150320277,
    "rank":67,
    "solver_rating":1571.0774088444,
    "conference":"Pac-12",
    "abbreviation":"WSU",
    "season":2019,
    "week":17,
    "as_of":"2026-06-21T03:41:18Z"
  },
  {
    "school":"Oregon State",
    "record":-0.05,
    "schedule":1555.6699245629,
    "results":1.0981978233,
    "elite_wins":0.0,
    "playoff_raw":0.0,
    "record_z":-0.5358911389,
    "schedule_z":0.4515332314,
    "results_z":0.8509097004,
    "elite_wins_z":-0.4518226538,
    "playoff_z":0.0,
    "wins":4,
    "losses":7,
    "poll_score":-0.7490312286,
    "poll_rating":1380.1550034169,
    "rank":68,
    "solver_rating":1515.5430287058,
    "conference":"Pac-12",
    "abbreviation":"ORST",
    "season":2019,
    "week":17,
    "as_of":"2026-06-21T03:41:18Z"
  },
  {
    "school":"Purdue",
    "record":-0.1,
    "schedule":1550.0764199565,
    "results":1.2636822646,
    "elite_wins":0.0,
    "playoff_raw":0.0,
    "record_z":-0.6667133531,
    "schedule_z":0.3820262073,
    "results_z":1.0446070298,
    "elite_wins_z":-0.4518226538,
    "playoff_z":0.0,
    "wins":4,
    "losses":8,
    "poll_score":-0.7518491906,
    "poll_rating":1379.7041295045,
    "rank":69,
    "solver_rating":1448.7208077772,
    "conference":"Big Ten",
    "abbreviation":"PUR",
    "season":2019,
    "week":17,
    "as_of":"2026-06-21T03:41:18Z"
  },
  {
    "school":"Tulsa",
    "record":-0.1,
    "schedule":1586.2522525843,
    "results":0.5806772941,
    "elite_wins":1.8273958431,
    "playoff_raw":0.0,
    "record_z":-0.6667133531,
    "schedule_z":0.8315609174,
    "results_z":0.2451588295,
    "elite_wins_z":0.1462374013,
    "playoff_z":0.0,
    "wins":4,
    "losses":8,
    "poll_score":-0.7610907147,
    "poll_rating":1378.2254856446,
    "rank":70,
    "solver_rating":1521.1434286613,
    "conference":"American Athletic",
    "abbreviation":"TLSA",
    "season":2019,
    "week":17,
    "as_of":"2026-06-21T03:41:18Z"
  },
  {
    "school":"West Virginia",
    "record":-0.05,
    "schedule":1554.4342223478,
    "results":0.9651944115,
    "elite_wins":0.0,
    "playoff_raw":0.0,
    "record_z":-0.5358911389,
    "schedule_z":0.4361779238,
    "results_z":0.6952309824,
    "elite_wins_z":-0.4518226538,
    "playoff_z":0.0,
    "wins":4,
    "losses":7,
    "poll_score":-0.7897722886,
    "poll_rating":1373.6364338184,
    "rank":71,
    "solver_rating":1425.2579887542,
    "conference":"Big 12",
    "abbreviation":"WVU",
    "season":2019,
    "week":17,
    "as_of":"2026-06-21T03:41:18Z"
  },
  {
    "school":"Liberty",
    "record":0.25,
    "schedule":1353.09994159,
    "results":-0.8434126252,
    "elite_wins":0.0,
    "playoff_raw":0.0,
    "record_z":0.2490421465,
    "schedule_z":-2.0656787295,
    "results_z":-1.4217194105,
    "elite_wins_z":-0.4518226538,
    "playoff_z":0.0,
    "wins":6,
    "losses":5,
    "poll_score":-0.7941661925,
    "poll_rating":1372.9334092077,
    "rank":72,
    "solver_rating":1466.9778727726,
    "conference":"FBS Independents",
    "abbreviation":"LIB",
    "season":2019,
    "week":17,
    "as_of":"2026-06-21T03:41:18Z"
  },
  {
    "school":"Tulane",
    "record":0.175,
    "schedule":1542.4182334205,
    "results":0.5075134789,
    "elite_wins":0.0,
    "playoff_raw":0.0,
    "record_z":0.0528088252,
    "schedule_z":0.286862657,
    "results_z":0.1595215605,
    "elite_wins_z":-0.4518226538,
    "playoff_z":0.0,
    "wins":6,
    "losses":6,
    "poll_score":-0.7981299179,
    "poll_rating":1372.2992131314,
    "rank":73,
    "solver_rating":1602.548712376,
    "conference":"American Athletic",
    "abbreviation":"TULN",
    "season":2019,
    "week":17,
    "as_of":"2026-06-21T03:41:18Z"
  },
  {
    "school":"Florida State",
    "record":0.0375,
    "schedule":1556.6134821911,
    "results":0.4769701811,
    "elite_wins":0.0,
    "playoff_raw":0.0,
    "record_z":-0.306952264,
    "schedule_z":0.4632582388,
    "results_z":0.1237710382,
    "elite_wins_z":-0.4518226538,
    "playoff_z":0.0,
    "wins":5,
    "losses":7,
    "poll_score":-0.8614408985,
    "poll_rating":1362.169456244,
    "rank":74,
    "solver_rating":1508.622764659,
    "conference":"ACC",
    "abbreviation":"FSU",
    "season":2019,
    "week":17,
    "as_of":"2026-06-21T03:41:18Z"
  },
  {
    "school":"Houston",
    "record":-0.2,
    "schedule":1582.6136248942,
    "results":0.7475526949,
    "elite_wins":0.0,
    "playoff_raw":0.0,
    "record_z":-0.9283577816,
    "schedule_z":0.7863459403,
    "results_z":0.4404842585,
    "elite_wins_z":-0.4518226538,
    "playoff_z":0.0,
    "wins":3,
    "losses":8,
    "poll_score":-0.8759158658,
    "poll_rating":1359.853461466,
    "rank":75,
    "solver_rating":1486.9476492309,
    "conference":"American Athletic",
    "abbreviation":"HOU",
    "season":2019,
    "week":17,
    "as_of":"2026-06-21T03:41:18Z"
  },
  {
    "school":"Maryland",
    "record":-0.35,
    "schedule":1595.5165504848,
    "results":0.9829139984,
    "elite_wins":0.0,
    "playoff_raw":0.0,
    "record_z":-1.3208244243,
    "schedule_z":0.9466826208,
    "results_z":0.7159715223,
    "elite_wins_z":-0.4518226538,
    "playoff_z":0.0,
    "wins":2,
    "losses":9,
    "poll_score":-0.8765661799,
    "poll_rating":1359.7494112113,
    "rank":76,
    "solver_rating":1188.0994089147,
    "conference":"Big Ten",
    "abbreviation":"MD",
    "season":2019,
    "week":17,
    "as_of":"2026-06-21T03:41:18Z"
  },
  {
    "school":"North Carolina",
    "record":0.175,
    "schedule":1522.4592160438,
    "results":0.4091480691,
    "elite_wins":0.0,
    "playoff_raw":0.0,
    "record_z":0.0528088252,
    "schedule_z":0.0388442857,
    "results_z":0.0443861614,
    "elite_wins_z":-0.4518226538,
    "playoff_z":0.0,
    "wins":6,
    "losses":6,
    "poll_score":-0.8803264554,
    "poll_rating":1359.1477671358,
    "rank":77,
    "solver_rating":1738.7859272992,
    "conference":"ACC",
    "abbreviation":"UNC",
    "season":2019,
    "week":17,
    "as_of":"2026-06-21T03:41:18Z"
  },
  {
    "school":"Vanderbilt",
    "record":-0.35,
    "schedule":1641.4210332777,
    "results":0.4976514593,
    "elite_wins":0.0,
    "playoff_raw":0.0,
    "record_z":-1.3208244243,
    "schedule_z":1.5171092529,
    "results_z":0.1479781982,
    "elite_wins_z":-0.4518226538,
    "playoff_z":0.0,
    "wins":2,
    "losses":9,
    "poll_score":-0.8873907187,
    "poll_rating":1358.017485014,
    "rank":78,
    "solver_rating":1309.6917918425,
    "conference":"SEC",
    "abbreviation":"VAN",
    "season":2019,
    "week":17,
    "as_of":"2026-06-21T03:41:18Z"
  },
  {
    "school":"Utah State",
    "record":0.175,
    "schedule":1562.5875458484,
    "results":-0.0213140406,
    "elite_wins":0.0,
    "playoff_raw":0.0,
    "record_z":0.0528088252,
    "schedule_z":0.537494235,
    "results_z":-0.4594639916,
    "elite_wins_z":-0.4518226538,
    "playoff_z":0.0,
    "wins":6,
    "losses":6,
    "poll_score":-0.8915475033,
    "poll_rating":1357.3523994762,
    "rank":79,
    "solver_rating":1402.2294942963,
    "conference":"Mountain West",
    "abbreviation":"USU",
    "season":2019,
    "week":17,
    "as_of":"2026-06-21T03:41:18Z"
  },
  {
    "school":"Illinois",
    "record":0.1115384615,
    "schedule":1463.1338786216,
    "results":0.6949524798,
    "elite_wins":2.4353522245,
    "playoff_raw":0.0,
    "record_z":-0.1132347544,
    "schedule_z":-0.6983550109,
    "results_z":0.3789164088,
    "elite_wins_z":0.3452060202,
    "playoff_z":0.0,
    "wins":6,
    "losses":7,
    "poll_score":-0.8938103576,
    "poll_rating":1356.9903427848,
    "rank":80,
    "solver_rating":1412.084208533,
    "conference":"Big Ten",
    "abbreviation":"ILL",
    "season":2019,
    "week":17,
    "as_of":"2026-06-21T03:41:18Z"
  },
  {
    "school":"Duke",
    "record":-0.05,
    "schedule":1577.2468457733,
    "results":0.2505991733,
    "elite_wins":0.0,
    "playoff_raw":0.0,
    "record_z":-0.5358911389,
    "schedule_z":0.7196562936,
    "results_z":-0.1411932046,
    "elite_wins_z":-0.4518226538,
    "playoff_z":0.0,
    "wins":4,
    "losses":7,
    "poll_score":-0.9281488521,
    "poll_rating":1351.4961836571,
    "rank":81,
    "solver_rating":1368.311954563,
    "conference":"ACC",
    "abbreviation":"DUKE",
    "season":2019,
    "week":17,
    "as_of":"2026-06-21T03:41:18Z"
  },
  {
    "school":"UCLA",
    "record":-0.1,
    "schedule":1547.324010041,
    "results":0.6004750043,
    "elite_wins":0.0,
    "playoff_raw":0.0,
    "record_z":-0.6667133531,
    "schedule_z":0.3478237106,
    "results_z":0.2683317849,
    "elite_wins_z":-0.4518226538,
    "playoff_z":0.0,
    "wins":4,
    "losses":8,
    "poll_score":-0.9456797986,
    "poll_rating":1348.6912322204,
    "rank":82,
    "solver_rating":1349.0553614159,
    "conference":"Pac-12",
    "abbreviation":"UCLA",
    "season":2019,
    "week":17,
    "as_of":"2026-06-21T03:41:18Z"
  },
  {
    "school":"Arizona",
    "record":-0.2,
    "schedule":1553.1792664404,
    "results":0.7430132529,
    "elite_wins":0.0,
    "playoff_raw":0.0,
    "record_z":-0.9283577816,
    "schedule_z":0.4205833625,
    "results_z":0.4351709022,
    "elite_wins_z":-0.4518226538,
    "playoff_z":0.0,
    "wins":3,
    "losses":8,
    "poll_score":-0.9576588385,
    "poll_rating":1346.7745858458,
    "rank":83,
    "solver_rating":1301.3696334235,
    "conference":"Pac-12",
    "abbreviation":"ARIZ",
    "season":2019,
    "week":17,
    "as_of":"2026-06-21T03:41:18Z"
  },
  {
    "school":"Boston College",
    "record":0.0375,
    "schedule":1522.0757019034,
    "results":0.431093229,
    "elite_wins":0.0,
    "playoff_raw":0.0,
    "record_z":-0.306952264,
    "schedule_z":0.0340785925,
    "results_z":0.0700726781,
    "elite_wins_z":-0.4518226538,
    "playoff_z":0.0,
    "wins":5,
    "losses":7,
    "poll_score":-0.9687480271,
    "poll_rating":1345.00031567,
    "rank":84,
    "solver_rating":1396.8691121213,
    "conference":"ACC",
    "abbreviation":"BC",
    "season":2019,
    "week":17,
    "as_of":"2026-06-21T03:41:18Z"
  },
  {
    "school":"Kansas",
    "record":-0.35,
    "schedule":1570.4775568701,
    "results":0.8019801199,
    "elite_wins":0.0,
    "playoff_raw":0.0,
    "record_z":-1.3208244243,
    "schedule_z":0.6355385248,
    "results_z":0.5041908328,
    "elite_wins_z":-0.4518226538,
    "playoff_z":0.0,
    "wins":2,
    "losses":9,
    "poll_score":-0.9958452465,
    "poll_rating":1340.6647605583,
    "rank":85,
    "solver_rating":1223.7020617791,
    "conference":"Big 12",
    "abbreviation":"KU",
    "season":2019,
    "week":17,
    "as_of":"2026-06-21T03:41:18Z"
  },
  {
    "school":"Northwestern",
    "record":-0.2375,
    "schedule":1534.3672536038,
    "results":0.7659020352,
    "elite_wins":0.0,
    "playoff_raw":0.0,
    "record_z":-1.0264744423,
    "schedule_z":0.1868181075,
    "results_z":0.4619619164,
    "elite_wins_z":-0.4518226538,
    "playoff_z":0.0,
    "wins":3,
    "losses":9,
    "poll_score":-1.0281676829,
    "poll_rating":1335.49317073,
    "rank":86,
    "solver_rating":1401.8238704999,
    "conference":"Big Ten",
    "abbreviation":"NU",
    "season":2019,
    "week":17,
    "as_of":"2026-06-21T03:41:18Z"
  },
  {
    "school":"Texas Tech",
    "record":-0.2,
    "schedule":1515.1680214924,
    "results":0.8572427543,
    "elite_wins":0.0,
    "playoff_raw":0.0,
    "record_z":-0.9283577816,
    "schedule_z":-0.051758882,
    "results_z":0.5688750087,
    "elite_wins_z":-0.4518226538,
    "playoff_z":0.0,
    "wins":3,
    "losses":8,
    "poll_score":-1.0294851467,
    "poll_rating":1335.2823765261,
    "rank":87,
    "solver_rating":1478.4369067939,
    "conference":"Big 12",
    "abbreviation":"TTU",
    "season":2019,
    "week":17,
    "as_of":"2026-06-21T03:41:18Z"
  },
  {
    "school":"Georgia Southern",
    "record":0.175,
    "schedule":1519.513407773,
    "results":-0.547607699,
    "elite_wins":1.9205961102,
    "playoff_raw":0.0,
    "record_z":0.0528088252,
    "schedule_z":0.0022385472,
    "results_z":-1.0754836932,
    "elite_wins_z":0.1767394718,
    "playoff_z":0.0,
    "wins":6,
    "losses":6,
    "poll_score":-1.0691497854,
    "poll_rating":1328.9360343382,
    "rank":88,
    "solver_rating":1518.544249975,
    "conference":"Sun Belt",
    "abbreviation":"GASO",
    "season":2019,
    "week":17,
    "as_of":"2026-06-21T03:41:18Z"
  },
  {
    "school":"Georgia Tech",
    "record":-0.2,
    "schedule":1572.0045318359,
    "results":0.1347160651,
    "elite_wins":0.0,
    "playoff_raw":0.0,
    "record_z":-0.9283577816,
    "schedule_z":0.6545132989,
    "results_z":-0.2768328358,
    "elite_wins_z":-0.4518226538,
    "playoff_z":0.0,
    "wins":3,
    "losses":8,
    "poll_score":-1.0770751496,
    "poll_rating":1327.6679760635,
    "rank":89,
    "solver_rating":1188.6566540089,
    "conference":"ACC",
    "abbreviation":"GT",
    "season":2019,
    "week":17,
    "as_of":"2026-06-21T03:41:18Z"
  },
  {
    "school":"Rutgers",
    "record":-0.375,
    "schedule":1544.0481475564,
    "results":0.7035755399,
    "elite_wins":0.0,
    "playoff_raw":0.0,
    "record_z":-1.3862355314,
    "schedule_z":0.3071165925,
    "results_z":0.3890095855,
    "elite_wins_z":-0.4518226538,
    "playoff_z":0.0,
    "wins":2,
    "losses":10,
    "poll_score":-1.1127484588,
    "poll_rating":1321.9602465879,
    "rank":90,
    "solver_rating":1131.4688489411,
    "conference":"Big Ten",
    "abbreviation":"RUTG",
    "season":2019,
    "week":17,
    "as_of":"2026-06-21T03:41:18Z"
  },
  {
    "school":"Southern Miss",
    "record":0.175,
    "schedule":1492.7269679373,
    "results":-0.1355839625,
    "elite_wins":0.0,
    "playoff_raw":0.0,
    "record_z":0.0528088252,
    "schedule_z":-0.3306199827,
    "results_z":-0.5932154099,
    "elite_wins_z":-0.4518226538,
    "playoff_z":0.0,
    "wins":6,
    "losses":6,
    "poll_score":-1.1146329716,
    "poll_rating":1321.65872455,
    "rank":91,
    "solver_rating":1489.4214754247,
    "conference":"Conference USA",
    "abbreviation":"USM",
    "season":2019,
    "week":17,
    "as_of":"2026-06-21T03:41:18Z"
  },
  {
    "school":"Miami",
    "record":0.0375,
    "schedule":1525.5595650767,
    "results":-0.1440406313,
    "elite_wins":0.0,
    "playoff_raw":0.0,
    "record_z":-0.306952264,
    "schedule_z":0.0773704066,
    "results_z":-0.6031138277,
    "elite_wins_z":-0.4518226538,
    "playoff_z":0.0,
    "wins":5,
    "losses":7,
    "poll_score":-1.1207885894,
    "poll_rating":1320.6738257025,
    "rank":92,
    "solver_rating":1483.559566396,
    "conference":"ACC",
    "abbreviation":"MIA",
    "season":2019,
    "week":17,
    "as_of":"2026-06-21T03:41:18Z"
  },
  {
    "school":"South Florida",
    "record":-0.2,
    "schedule":1536.6178263337,
    "results":0.2297495491,
    "elite_wins":0.0,
    "playoff_raw":0.0,
    "record_z":-0.9283577816,
    "schedule_z":0.2147845837,
    "results_z":-0.1655974115,
    "elite_wins_z":-0.4518226538,
    "playoff_z":0.0,
    "wins":3,
    "losses":8,
    "poll_score":-1.1471189651,
    "poll_rating":1316.460965585,
    "rank":93,
    "solver_rating":1328.2444858695,
    "conference":"American Athletic",
    "abbreviation":"USF",
    "season":2019,
    "week":17,
    "as_of":"2026-06-21T03:41:18Z"
  },
  {
    "school":"BYU",
    "record":0.175,
    "schedule":1479.4173918224,
    "results":-0.4057767341,
    "elite_wins":0.0,
    "playoff_raw":0.0,
    "record_z":0.0528088252,
    "schedule_z":-0.4960098579,
    "results_z":-0.9094724421,
    "elite_wins_z":-0.4518226538,
    "playoff_z":0.0,
    "wins":6,
    "losses":6,
    "poll_score":-1.2269204318,
    "poll_rating":1303.6927309059,
    "rank":94,
    "solver_rating":1548.1530672846,
    "conference":"FBS Independents",
    "abbreviation":"BYU",
    "season":2019,
    "week":17,
    "as_of":"2026-06-21T03:41:18Z"
  },
  {
    "school":"Syracuse",
    "record":-0.05,
    "schedule":1472.5132882785,
    "results":0.2010175342,
    "elite_wins":0.0,
    "playoff_raw":0.0,
    "record_z":-0.5358911389,
    "schedule_z":-0.5818028849,
    "results_z":-0.1992278513,
    "elite_wins_z":-0.4518226538,
    "playoff_z":0.0,
    "wins":4,
    "losses":7,
    "poll_score":-1.2283981866,
    "poll_rating":1303.456290138,
    "rank":95,
    "solver_rating":1415.6615963365,
    "conference":"ACC",
    "abbreviation":"SYR",
    "season":2019,
    "week":17,
    "as_of":"2026-06-21T03:41:18Z"
  },
  {
    "school":"NC State",
    "record":-0.2,
    "schedule":1503.7588859918,
    "results":0.1789590473,
    "elite_wins":0.0,
    "playoff_raw":0.0,
    "record_z":-0.9283577816,
    "schedule_z":-0.1935331564,
    "results_z":-0.2250470157,
    "elite_wins_z":-0.4518226538,
    "playoff_z":0.0,
    "wins":3,
    "losses":8,
    "poll_score":-1.2512167729,
    "poll_rating":1299.8053163319,
    "rank":96,
    "solver_rating":1210.3417069396,
    "conference":"ACC",
    "abbreviation":"NCSU",
    "season":2019,
    "week":17,
    "as_of":"2026-06-21T03:41:18Z"
  },
  {
    "school":"Nevada",
    "record":0.175,
    "schedule":1462.246948937,
    "results":-0.4423050212,
    "elite_wins":0.0,
    "playoff_raw":0.0,
    "record_z":0.0528088252,
    "schedule_z":-0.7093763378,
    "results_z":-0.9522283145,
    "elite_wins_z":-0.4518226538,
    "playoff_z":0.0,
    "wins":6,
    "losses":6,
    "poll_score":-1.2841224668,
    "poll_rating":1294.5404053125,
    "rank":97,
    "solver_rating":1339.0051902211,
    "conference":"Mountain West",
    "abbreviation":"NEV",
    "season":2019,
    "week":17,
    "as_of":"2026-06-21T03:41:18Z"
  },
  {
    "school":"Georgia State",
    "record":0.175,
    "schedule":1463.2187886742,
    "results":-0.4521757925,
    "elite_wins":0.0,
    "playoff_raw":0.0,
    "record_z":0.0528088252,
    "schedule_z":-0.6972998861,
    "results_z":-0.9637819206,
    "elite_wins_z":-0.4518226538,
    "playoff_z":0.0,
    "wins":6,
    "losses":6,
    "poll_score":-1.2842385129,
    "poll_rating":1294.5218379377,
    "rank":98,
    "solver_rating":1314.6303294121,
    "conference":"Sun Belt",
    "abbreviation":"GAST",
    "season":2019,
    "week":17,
    "as_of":"2026-06-21T03:41:18Z"
  },
  {
    "school":"UL Monroe",
    "record":-0.05,
    "schedule":1501.1712066017,
    "results":-0.2979072917,
    "elite_wins":0.0,
    "playoff_raw":0.0,
    "record_z":-0.5358911389,
    "schedule_z":-0.2256886486,
    "results_z":-0.7832126998,
    "elite_wins_z":-0.4518226538,
    "playoff_z":0.0,
    "wins":4,
    "losses":7,
    "poll_score":-1.2902094183,
    "poll_rating":1293.566493073,
    "rank":99,
    "solver_rating":1381.7879572609,
    "conference":"Sun Belt",
    "abbreviation":"ULM",
    "season":2019,
    "week":17,
    "as_of":"2026-06-21T03:41:18Z"
  },
  {
    "school":"San Jos\u00e9 State",
    "record":-0.05,
    "schedule":1473.4650596554,
    "results":-0.0847473984,
    "elite_wins":0.0,
    "playoff_raw":0.0,
    "record_z":-0.5358911389,
    "schedule_z":-0.5699758103,
    "results_z":-0.5337118901,
    "elite_wins_z":-0.4518226538,
    "playoff_z":0.0,
    "wins":4,
    "losses":7,
    "poll_score":-1.3060723995,
    "poll_rating":1291.028416073,
    "rank":100,
    "solver_rating":1431.8380168067,
    "conference":"Mountain West",
    "abbreviation":"SJSU",
    "season":2019,
    "week":17,
    "as_of":"2026-06-21T03:41:18Z"
  },
  {
    "school":"Kent State",
    "record":0.175,
    "schedule":1444.2336636884,
    "results":-0.4004701809,
    "elite_wins":0.0,
    "playoff_raw":0.0,
    "record_z":0.0528088252,
    "schedule_z":-0.9332162988,
    "results_z":-0.9032611924,
    "elite_wins_z":-0.4518226538,
    "playoff_z":0.0,
    "wins":6,
    "losses":6,
    "poll_score":-1.3216151489,
    "poll_rating":1288.5415761765,
    "rank":101,
    "solver_rating":1473.5510447489,
    "conference":"Mid-American",
    "abbreviation":"KENT",
    "season":2019,
    "week":17,
    "as_of":"2026-06-21T03:41:18Z"
  },
  {
    "school":"Charlotte",
    "record":0.175,
    "schedule":1467.8907034626,
    "results":-0.7259044862,
    "elite_wins":0.0,
    "playoff_raw":0.0,
    "record_z":0.0528088252,
    "schedule_z":-0.639244889,
    "results_z":-1.2841777025,
    "elite_wins_z":-0.4518226538,
    "playoff_z":0.0,
    "wins":6,
    "losses":6,
    "poll_score":-1.3483614012,
    "poll_rating":1284.2621758133,
    "rank":102,
    "solver_rating":1409.6908347319,
    "conference":"Conference USA",
    "abbreviation":"CLT",
    "season":2019,
    "week":17,
    "as_of":"2026-06-21T03:41:18Z"
  },
  {
    "school":"Fresno State",
    "record":-0.2,
    "schedule":1486.1202136427,
    "results":-0.1326607334,
    "elite_wins":0.0,
    "playoff_raw":0.0,
    "record_z":-0.9283577816,
    "schedule_z":-0.4127180344,
    "results_z":-0.5897938092,
    "elite_wins_z":-0.4518226538,
    "playoff_z":0.0,
    "wins":3,
    "losses":8,
    "poll_score":-1.3869766765,
    "poll_rating":1278.0837317558,
    "rank":103,
    "solver_rating":1444.0442065577,
    "conference":"Mountain West",
    "abbreviation":"FRES",
    "season":2019,
    "week":17,
    "as_of":"2026-06-21T03:41:18Z"
  },
  {
    "school":"Colorado State",
    "record":-0.2,
    "schedule":1446.8852190108,
    "results":0.151351284,
    "elite_wins":0.0,
    "playoff_raw":0.0,
    "record_z":-0.9283577816,
    "schedule_z":-0.9002670598,
    "results_z":-0.2573615342,
    "elite_wins_z":-0.4518226538,
    "playoff_z":0.0,
    "wins":3,
    "losses":8,
    "poll_score":-1.4144537161,
    "poll_rating":1273.6874054218,
    "rank":104,
    "solver_rating":1430.522848494,
    "conference":"Mountain West",
    "abbreviation":"CSU",
    "season":2019,
    "week":17,
    "as_of":"2026-06-21T03:41:18Z"
  },
  {
    "school":"Middle Tennessee",
    "record":-0.2,
    "schedule":1500.9071396339,
    "results":-0.3970349988,
    "elite_wins":0.0,
    "playoff_raw":0.0,
    "record_z":-0.9283577816,
    "schedule_z":-0.2289700456,
    "results_z":-0.8992403577,
    "elite_wins_z":-0.4518226538,
    "playoff_z":0.0,
    "wins":3,
    "losses":8,
    "poll_score":-1.4208192906,
    "poll_rating":1272.6689135007,
    "rank":105,
    "solver_rating":1450.5278555001,
    "conference":"Conference USA",
    "abbreviation":"MTSU",
    "season":2019,
    "week":17,
    "as_of":"2026-06-21T03:41:18Z"
  },
  {
    "school":"Ball State",
    "record":-0.05,
    "schedule":1457.4236368178,
    "results":-0.356933364,
    "elite_wins":0.0,
    "playoff_raw":0.0,
    "record_z":-0.5358911389,
    "schedule_z":-0.769312656,
    "results_z":-0.8523019295,
    "elite_wins_z":-0.4518226538,
    "playoff_z":0.0,
    "wins":4,
    "losses":7,
    "poll_score":-1.426388115,
    "poll_rating":1271.7779015938,
    "rank":106,
    "solver_rating":1518.1249976743,
    "conference":"Mid-American",
    "abbreviation":"BALL",
    "season":2019,
    "week":17,
    "as_of":"2026-06-21T03:41:18Z"
  },
  {
    "school":"Army",
    "record":-0.2,
    "schedule":1462.3803077582,
    "results":-0.0651566077,
    "elite_wins":0.0,
    "playoff_raw":0.0,
    "record_z":-0.9283577816,
    "schedule_z":-0.7077191702,
    "results_z":-0.5107811312,
    "elite_wins_z":-0.4518226538,
    "playoff_z":0.0,
    "wins":3,
    "losses":8,
    "poll_score":-1.4329138837,
    "poll_rating":1270.7337786132,
    "rank":107,
    "solver_rating":1483.7495886152,
    "conference":"FBS Independents",
    "abbreviation":"ARMY",
    "season":2019,
    "week":17,
    "as_of":"2026-06-21T03:41:18Z"
  },
  {
    "school":"UNLV",
    "record":-0.2,
    "schedule":1479.8861797498,
    "results":-0.2837552824,
    "elite_wins":0.0,
    "playoff_raw":0.0,
    "record_z":-0.9283577816,
    "schedule_z":-0.4901845201,
    "results_z":-0.7666479618,
    "elite_wins_z":-0.4518226538,
    "playoff_z":0.0,
    "wins":3,
    "losses":8,
    "poll_score":-1.4464643,
    "poll_rating":1268.5657120012,
    "rank":108,
    "solver_rating":1317.7647350776,
    "conference":"Mountain West",
    "abbreviation":"UNLV",
    "season":2019,
    "week":17,
    "as_of":"2026-06-21T03:41:18Z"
  },
  {
    "school":"Toledo",
    "record":0.1,
    "schedule":1452.5199231387,
    "results":-0.7710325933,
    "elite_wins":0.0,
    "playoff_raw":0.0,
    "record_z":-0.1434244962,
    "schedule_z":-0.8302480747,
    "results_z":-1.3369995494,
    "elite_wins_z":-0.4518226538,
    "playoff_z":0.0,
    "wins":5,
    "losses":6,
    "poll_score":-1.4540800088,
    "poll_rating":1267.3471985851,
    "rank":109,
    "solver_rating":1235.6909825063,
    "conference":"Mid-American",
    "abbreviation":"TOL",
    "season":2019,
    "week":17,
    "as_of":"2026-06-21T03:41:18Z"
  },
  {
    "school":"Western Michigan",
    "record":0.175,
    "schedule":1392.4386402477,
    "results":-0.4387723297,
    "elite_wins":0.0,
    "playoff_raw":0.0,
    "record_z":0.0528088252,
    "schedule_z":-1.5768410383,
    "results_z":-0.9480933463,
    "elite_wins_z":-0.4518226538,
    "playoff_z":0.0,
    "wins":6,
    "losses":6,
    "poll_score":-1.4739723085,
    "poll_rating":1264.1644306367,
    "rank":110,
    "solver_rating":1519.7866930658,
    "conference":"Mid-American",
    "abbreviation":"WMU",
    "season":2019,
    "week":17,
    "as_of":"2026-06-21T03:41:18Z"
  },
  {
    "school":"Ohio",
    "record":0.175,
    "schedule":1398.5130345599,
    "results":-0.6768881129,
    "elite_wins":0.0,
    "playoff_raw":0.0,
    "record_z":0.0528088252,
    "schedule_z":-1.501358295,
    "results_z":-1.2268046919,
    "elite_wins_z":-0.4518226538,
    "playoff_z":0.0,
    "wins":6,
    "losses":6,
    "poll_score":-1.524256828,
    "poll_rating":1256.1189075275,
    "rank":111,
    "solver_rating":1586.4993968892,
    "conference":"Mid-American",
    "abbreviation":"OHIO",
    "season":2019,
    "week":17,
    "as_of":"2026-06-21T03:41:18Z"
  },
  {
    "school":"UTSA",
    "record":-0.2,
    "schedule":1468.9262373274,
    "results":-0.4674062347,
    "elite_wins":0.0,
    "playoff_raw":0.0,
    "record_z":-0.9283577816,
    "schedule_z":-0.6263769497,
    "results_z":-0.9816089498,
    "elite_wins_z":-0.4518226538,
    "playoff_z":0.0,
    "wins":3,
    "losses":8,
    "poll_score":-1.5280172716,
    "poll_rating":1255.5172365362,
    "rank":112,
    "solver_rating":1241.5281635539,
    "conference":"Conference USA",
    "abbreviation":"UTSA",
    "season":2019,
    "week":17,
    "as_of":"2026-06-21T03:41:18Z"
  },
  {
    "school":"New Mexico",
    "record":-0.5,
    "schedule":1515.9984640419,
    "results":-0.2359130345,
    "elite_wins":0.0,
    "playoff_raw":0.0,
    "record_z":-1.713291067,
    "schedule_z":-0.0414394858,
    "results_z":-0.7106492493,
    "elite_wins_z":-0.4518226538,
    "playoff_z":0.0,
    "wins":1,
    "losses":10,
    "poll_score":-1.5383833557,
    "poll_rating":1253.8586630944,
    "rank":113,
    "solver_rating":1202.6349283464,
    "conference":"Mountain West",
    "abbreviation":"UNM",
    "season":2019,
    "week":17,
    "as_of":"2026-06-21T03:41:18Z"
  },
  {
    "school":"Texas State",
    "record":-0.35,
    "schedule":1505.9958461323,
    "results":-0.5098291652,
    "elite_wins":0.0,
    "playoff_raw":0.0,
    "record_z":-1.3208244243,
    "schedule_z":-0.1657358355,
    "results_z":-1.0312644237,
    "elite_wins_z":-0.4518226538,
    "playoff_z":0.0,
    "wins":2,
    "losses":9,
    "poll_score":-1.5406348674,
    "poll_rating":1253.4984212239,
    "rank":114,
    "solver_rating":1216.3243172083,
    "conference":"Sun Belt",
    "abbreviation":"TXST",
    "season":2019,
    "week":17,
    "as_of":"2026-06-21T03:41:18Z"
  },
  {
    "school":"Troy",
    "record":-0.05,
    "schedule":1413.8003004034,
    "results":-0.4592768457,
    "elite_wins":0.0,
    "playoff_raw":0.0,
    "record_z":-0.5358911389,
    "schedule_z":-1.3113928921,
    "results_z":-0.9720936085,
    "elite_wins_z":-0.4518226538,
    "playoff_z":0.0,
    "wins":4,
    "losses":7,
    "poll_score":-1.57439577,
    "poll_rating":1248.0966768066,
    "rank":115,
    "solver_rating":1362.4605915739,
    "conference":"Sun Belt",
    "abbreviation":"TROY",
    "season":2019,
    "week":17,
    "as_of":"2026-06-21T03:41:18Z"
  },
  {
    "school":"East Carolina",
    "record":-0.32,
    "schedule":1448.867889999,
    "results":-0.3062114885,
    "elite_wins":0.0,
    "playoff_raw":0.0,
    "record_z":-1.2423310957,
    "schedule_z":-0.875629633,
    "results_z":-0.7929326513,
    "elite_wins_z":-0.4518226538,
    "playoff_z":0.0,
    "wins":2,
    "losses":8,
    "poll_score":-1.619203612,
    "poll_rating":1240.9274220786,
    "rank":116,
    "solver_rating":1263.1874460867,
    "conference":"American Athletic",
    "abbreviation":"ECU",
    "season":2019,
    "week":17,
    "as_of":"2026-06-21T03:41:18Z"
  },
  {
    "school":"Eastern Michigan",
    "record":0.0375,
    "schedule":1410.0276728646,
    "results":-0.8185347019,
    "elite_wins":0.0,
    "playoff_raw":0.0,
    "record_z":-0.306952264,
    "schedule_z":-1.3582730025,
    "results_z":-1.3926001333,
    "elite_wins_z":-0.4518226538,
    "playoff_z":0.0,
    "wins":5,
    "losses":7,
    "poll_score":-1.6261068527,
    "poll_rating":1239.8229035643,
    "rank":117,
    "solver_rating":1410.5139286952,
    "conference":"Mid-American",
    "abbreviation":"EMU",
    "season":2019,
    "week":17,
    "as_of":"2026-06-21T03:41:18Z"
  },
  {
    "school":"South Alabama",
    "record":-0.5,
    "schedule":1503.2829743187,
    "results":-0.4407630943,
    "elite_wins":0.0,
    "playoff_raw":0.0,
    "record_z":-1.713291067,
    "schedule_z":-0.1994470166,
    "results_z":-0.9504235097,
    "elite_wins_z":-0.4518226538,
    "playoff_z":0.0,
    "wins":1,
    "losses":10,
    "poll_score":-1.6306908349,
    "poll_rating":1239.0894664113,
    "rank":118,
    "solver_rating":1280.5141266667,
    "conference":"Sun Belt",
    "abbreviation":"USA",
    "season":2019,
    "week":17,
    "as_of":"2026-06-21T03:41:18Z"
  },
  {
    "school":"Florida International",
    "record":0.0375,
    "schedule":1402.4231391014,
    "results":-0.8197542646,
    "elite_wins":0.0,
    "playoff_raw":0.0,
    "record_z":-0.306952264,
    "schedule_z":-1.4527698429,
    "results_z":-1.3940276153,
    "elite_wins_z":-0.4518226538,
    "playoff_z":0.0,
    "wins":5,
    "losses":7,
    "poll_score":-1.6472387533,
    "poll_rating":1236.4417994768,
    "rank":119,
    "solver_rating":1382.3808194073,
    "conference":"Conference USA",
    "abbreviation":"FIU",
    "season":2019,
    "week":17,
    "as_of":"2026-06-21T03:41:18Z"
  },
  {
    "school":"Northern Illinois",
    "record":-0.05,
    "schedule":1422.9772232821,
    "results":-0.8232684202,
    "elite_wins":0.0,
    "playoff_raw":0.0,
    "record_z":-0.5358911389,
    "schedule_z":-1.1973569442,
    "results_z":-1.3981408874,
    "elite_wins_z":-0.4518226538,
    "playoff_z":0.0,
    "wins":4,
    "losses":7,
    "poll_score":-1.6515592083,
    "poll_rating":1235.7505266651,
    "rank":120,
    "solver_rating":1307.5481879553,
    "conference":"Mid-American",
    "abbreviation":"NIU",
    "season":2019,
    "week":17,
    "as_of":"2026-06-21T03:41:18Z"
  },
  {
    "school":"Rice",
    "record":-0.2375,
    "schedule":1459.7067865035,
    "results":-0.8550997076,
    "elite_wins":0.0,
    "playoff_raw":0.0,
    "record_z":-1.0264744423,
    "schedule_z":-0.7409413662,
    "results_z":-1.4353989845,
    "elite_wins_z":-0.4518226538,
    "playoff_z":0.0,
    "wins":3,
    "losses":9,
    "poll_score":-1.6876413834,
    "poll_rating":1229.9773786629,
    "rank":121,
    "solver_rating":1344.816019947,
    "conference":"Conference USA",
    "abbreviation":"RICE",
    "season":2019,
    "week":17,
    "as_of":"2026-06-21T03:41:18Z"
  },
  {
    "school":"Bowling Green",
    "record":-0.35,
    "schedule":1481.166182067,
    "results":-0.8607478833,
    "elite_wins":0.0,
    "playoff_raw":0.0,
    "record_z":-1.3208244243,
    "schedule_z":-0.4742787225,
    "results_z":-1.4420100987,
    "elite_wins_z":-0.4518226538,
    "playoff_z":0.0,
    "wins":2,
    "losses":9,
    "poll_score":-1.7070932645,
    "poll_rating":1226.865077682,
    "rank":122,
    "solver_rating":973.3810300042,
    "conference":"Mid-American",
    "abbreviation":"BGSU",
    "season":2019,
    "week":17,
    "as_of":"2026-06-21T03:41:18Z"
  },
  {
    "school":"New Mexico State",
    "record":-0.5,
    "schedule":1495.7421636327,
    "results":-0.7468347068,
    "elite_wins":0.0,
    "playoff_raw":0.0,
    "record_z":-1.713291067,
    "schedule_z":-0.2931520097,
    "results_z":-1.3086762462,
    "elite_wins_z":-0.4518226538,
    "playoff_z":0.0,
    "wins":1,
    "losses":10,
    "poll_score":-1.7372865902,
    "poll_rating":1222.0341455724,
    "rank":123,
    "solver_rating":1171.2448994144,
    "conference":"FBS Independents",
    "abbreviation":"NMSU",
    "season":2019,
    "week":17,
    "as_of":"2026-06-21T03:41:18Z"
  },
  {
    "school":"UConn",
    "record":-0.5,
    "schedule":1455.1485880969,
    "results":-0.4507753041,
    "elite_wins":0.0,
    "playoff_raw":0.0,
    "record_z":-1.713291067,
    "schedule_z":-0.7975832802,
    "results_z":-0.9621426675,
    "elite_wins_z":-0.4518226538,
    "playoff_z":0.0,
    "wins":1,
    "losses":10,
    "poll_score":-1.7650934108,
    "poll_rating":1217.5850542726,
    "rank":124,
    "solver_rating":1002.3792902747,
    "conference":"American Athletic",
    "abbreviation":"CONN",
    "season":2019,
    "week":17,
    "as_of":"2026-06-21T03:41:18Z"
  },
  {
    "school":"Coastal Carolina",
    "record":-0.05,
    "schedule":1375.438711786,
    "results":-0.8102848277,
    "elite_wins":0.0,
    "playoff_raw":0.0,
    "record_z":-0.5358911389,
    "schedule_z":-1.7880886409,
    "results_z":-1.3829437657,
    "elite_wins_z":-0.4518226538,
    "playoff_z":0.0,
    "wins":4,
    "losses":7,
    "poll_score":-1.7778728724,
    "poll_rating":1215.5403404141,
    "rank":125,
    "solver_rating":1328.7310050754,
    "conference":"Sun Belt",
    "abbreviation":"CCU",
    "season":2019,
    "week":17,
    "as_of":"2026-06-21T03:41:18Z"
  },
  {
    "school":"North Texas",
    "record":-0.2,
    "schedule":1418.7990109882,
    "results":-0.9543622157,
    "elite_wins":0.0,
    "playoff_raw":0.0,
    "record_z":-0.9283577816,
    "schedule_z":-1.2492770056,
    "results_z":-1.5515844251,
    "elite_wins_z":-0.4518226538,
    "playoff_z":0.0,
    "wins":3,
    "losses":8,
    "poll_score":-1.801849398,
    "poll_rating":1211.704096318,
    "rank":126,
    "solver_rating":1340.6780979452,
    "conference":"Conference USA",
    "abbreviation":"UNT",
    "season":2019,
    "week":17,
    "as_of":"2026-06-21T03:41:18Z"
  },
  {
    "school":"Old Dominion",
    "record":-0.65,
    "schedule":1487.2387426442,
    "results":-0.6143814572,
    "elite_wins":0.0,
    "playoff_raw":0.0,
    "record_z":-2.1057577097,
    "schedule_z":-0.3988187659,
    "results_z":-1.1536414857,
    "elite_wins_z":-0.4518226538,
    "playoff_z":0.0,
    "wins":0,
    "losses":11,
    "poll_score":-1.8253662611,
    "poll_rating":1207.9413982173,
    "rank":127,
    "solver_rating":1176.8190402958,
    "conference":"Conference USA",
    "abbreviation":"ODU",
    "season":2019,
    "week":17,
    "as_of":"2026-06-21T03:41:18Z"
  },
  {
    "school":"UTEP",
    "record":-0.65,
    "schedule":1379.4397825875,
    "results":-1.237473389,
    "elite_wins":0.0,
    "playoff_raw":0.0,
    "record_z":-2.1057577097,
    "schedule_z":-1.7383698073,
    "results_z":-1.8829622741,
    "elite_wins_z":-0.4518226538,
    "playoff_z":0.0,
    "wins":0,
    "losses":11,
    "poll_score":-2.2951044794,
    "poll_rating":1132.7832832887,
    "rank":128,
    "solver_rating":1070.5604396331,
    "conference":"Conference USA",
    "abbreviation":"UTEP",
    "season":2019,
    "week":17,
    "as_of":"2026-06-21T03:41:18Z"
  },
  {
    "school":"Massachusetts",
    "record":-0.5,
    "schedule":1326.2603932801,
    "results":-1.6018657662,
    "elite_wins":0.0,
    "playoff_raw":0.0,
    "record_z":-1.713291067,
    "schedule_z":-2.3991972056,
    "results_z":-2.3094786872,
    "elite_wins_z":-0.4518226538,
    "playoff_z":0.0,
    "wins":1,
    "losses":10,
    "poll_score":-2.4408091191,
    "poll_rating":1109.4705409391,
    "rank":129,
    "solver_rating":714.7844497068,
    "conference":"FBS Independents",
    "abbreviation":"MASS",
    "season":2019,
    "week":17,
    "as_of":"2026-06-21T03:41:18Z"
  },
  {
    "school":"Akron",
    "record":-0.65,
    "schedule":1349.2898561511,
    "results":-1.6507439171,
    "elite_wins":0.0,
    "playoff_raw":0.0,
    "record_z":-2.1057577097,
    "schedule_z":-2.1130243061,
    "results_z":-2.3666899104,
    "elite_wins_z":-0.4518226538,
    "playoff_z":0.0,
    "wins":0,
    "losses":12,
    "poll_score":-2.4936231019,
    "poll_rating":1101.0203036974,
    "rank":130,
    "solver_rating":876.2221991542,
    "conference":"Mid-American",
    "abbreviation":"AKR",
    "season":2019,
    "week":17,
    "as_of":"2026-06-21T03:41:18Z"
  }
]