[
  {
    "school":"Notre Dame",
    "quality_z":2.1639861275,
    "game_value_z":0.9858974187,
    "market_z":0.0,
    "talent_prior_z":2.139982894,
    "solver_rating":2055.0892054536,
    "power_score":1.5126554529,
    "power_rating":1742.0248724669,
    "rank":1,
    "conference":"FBS Independents",
    "abbreviation":"ND",
    "season":2025,
    "week":16,
    "as_of":"2026-06-19T00:37:11Z"
  },
  {
    "school":"Texas Tech",
    "quality_z":1.8770872978,
    "game_value_z":1.5304994229,
    "market_z":0.0,
    "talent_prior_z":-1.8650689151,
    "solver_rating":2082.482919843,
    "power_score":1.498078026,
    "power_rating":1739.6924841649,
    "rank":2,
    "conference":"Big 12",
    "abbreviation":"TTU",
    "season":2025,
    "week":16,
    "as_of":"2026-06-19T00:37:11Z"
  },
  {
    "school":"Miami",
    "quality_z":1.8775539409,
    "game_value_z":1.1663481786,
    "market_z":0.0,
    "talent_prior_z":0.3998142637,
    "solver_rating":1924.0447510897,
    "power_score":1.3980648748,
    "power_rating":1723.6903799688,
    "rank":3,
    "conference":"ACC",
    "abbreviation":"MIA",
    "season":2025,
    "week":16,
    "as_of":"2026-06-19T00:37:11Z"
  },
  {
    "school":"Indiana",
    "quality_z":1.5246964943,
    "game_value_z":1.5750931141,
    "market_z":0.0,
    "talent_prior_z":-1.7685534675,
    "solver_rating":2056.2314664223,
    "power_score":1.3082441782,
    "power_rating":1709.3190685085,
    "rank":4,
    "conference":"Big Ten",
    "abbreviation":"IU",
    "season":2025,
    "week":16,
    "as_of":"2026-06-19T00:37:11Z"
  },
  {
    "school":"Oregon",
    "quality_z":1.5441501031,
    "game_value_z":1.4768419928,
    "market_z":0.0,
    "talent_prior_z":1.4307828749,
    "solver_rating":1932.0498295299,
    "power_score":1.2923452019,
    "power_rating":1706.7752323023,
    "rank":5,
    "conference":"Big Ten",
    "abbreviation":"ORE",
    "season":2025,
    "week":16,
    "as_of":"2026-06-19T00:37:11Z"
  },
  {
    "school":"Vanderbilt",
    "quality_z":1.3877470791,
    "game_value_z":1.533737326,
    "market_z":0.0,
    "talent_prior_z":0.8545647573,
    "solver_rating":1838.1896529231,
    "power_score":1.2183080295,
    "power_rating":1694.9292847125,
    "rank":6,
    "conference":"SEC",
    "abbreviation":"VAN",
    "season":2025,
    "week":16,
    "as_of":"2026-06-19T00:37:11Z"
  },
  {
    "school":"Ohio State",
    "quality_z":1.4768832716,
    "game_value_z":1.1619793203,
    "market_z":0.0,
    "talent_prior_z":2.8558092818,
    "solver_rating":1979.1175310721,
    "power_score":1.1670566353,
    "power_rating":1686.7290616434,
    "rank":7,
    "conference":"Big Ten",
    "abbreviation":"OSU",
    "season":2025,
    "week":16,
    "as_of":"2026-06-19T00:37:11Z"
  },
  {
    "school":"South Florida",
    "quality_z":1.8151281554,
    "game_value_z":0.2217240826,
    "market_z":0.0,
    "talent_prior_z":1.0440159521,
    "solver_rating":1888.123143547,
    "power_score":1.1021277678,
    "power_rating":1676.340442844,
    "rank":8,
    "conference":"American Athletic",
    "abbreviation":"USF",
    "season":2025,
    "week":16,
    "as_of":"2026-06-19T00:37:11Z"
  },
  {
    "school":"Ole Miss",
    "quality_z":1.137706093,
    "game_value_z":1.4894565425,
    "market_z":0.0,
    "talent_prior_z":-1.9334078252,
    "solver_rating":1771.7195675997,
    "power_score":1.0627025854,
    "power_rating":1670.0324136682,
    "rank":9,
    "conference":"SEC",
    "abbreviation":"MISS",
    "season":2025,
    "week":16,
    "as_of":"2026-06-19T00:37:11Z"
  },
  {
    "school":"Toledo",
    "quality_z":1.9479711408,
    "game_value_z":-0.2641911013,
    "market_z":0.0,
    "talent_prior_z":0.2346158776,
    "solver_rating":1813.5712926844,
    "power_score":1.0445075937,
    "power_rating":1667.1212149871,
    "rank":10,
    "conference":"Mid-American",
    "abbreviation":"TOL",
    "season":2025,
    "week":16,
    "as_of":"2026-06-19T00:37:11Z"
  },
  {
    "school":"Georgia",
    "quality_z":1.2868089689,
    "game_value_z":1.0150296634,
    "market_z":0.0,
    "talent_prior_z":2.3967468538,
    "solver_rating":1830.3027380619,
    "power_score":1.017571966,
    "power_rating":1662.811514561,
    "rank":11,
    "conference":"SEC",
    "abbreviation":"UGA",
    "season":2025,
    "week":16,
    "as_of":"2026-06-19T00:37:11Z"
  },
  {
    "school":"SMU",
    "quality_z":1.1188614861,
    "game_value_z":1.0724126393,
    "market_z":0.0,
    "talent_prior_z":-0.2356511834,
    "solver_rating":1801.3975660273,
    "power_score":0.9370477438,
    "power_rating":1649.9276390035,
    "rank":12,
    "conference":"ACC",
    "abbreviation":"SMU",
    "season":2025,
    "week":16,
    "as_of":"2026-06-19T00:37:11Z"
  },
  {
    "school":"James Madison",
    "quality_z":1.5349505156,
    "game_value_z":-0.0559112766,
    "market_z":0.0,
    "talent_prior_z":0.5070029151,
    "solver_rating":1919.8879036272,
    "power_score":0.8649756987,
    "power_rating":1638.3961117852,
    "rank":13,
    "conference":"Sun Belt",
    "abbreviation":"JMU",
    "season":2025,
    "week":16,
    "as_of":"2026-06-19T00:37:11Z"
  },
  {
    "school":"Washington",
    "quality_z":0.9600907146,
    "game_value_z":1.140121833,
    "market_z":0.0,
    "talent_prior_z":0.0405323461,
    "solver_rating":1719.7731553472,
    "power_score":0.8646304923,
    "power_rating":1638.3408787679,
    "rank":14,
    "conference":"Big Ten",
    "abbreviation":"WASH",
    "season":2025,
    "week":16,
    "as_of":"2026-06-19T00:37:11Z"
  },
  {
    "school":"Utah",
    "quality_z":1.0574426583,
    "game_value_z":0.7471040336,
    "market_z":0.0,
    "talent_prior_z":-0.6474086218,
    "solver_rating":1806.7385676971,
    "power_score":0.8122366817,
    "power_rating":1629.9578690763,
    "rank":15,
    "conference":"Big 12",
    "abbreviation":"UTAH",
    "season":2025,
    "week":16,
    "as_of":"2026-06-19T00:37:11Z"
  },
  {
    "school":"Missouri",
    "quality_z":0.6497735961,
    "game_value_z":1.3908020826,
    "market_z":0.0,
    "talent_prior_z":-0.3037840424,
    "solver_rating":1635.3622713,
    "power_score":0.7556806394,
    "power_rating":1620.9089023072,
    "rank":16,
    "conference":"SEC",
    "abbreviation":"MIZ",
    "season":2025,
    "week":16,
    "as_of":"2026-06-19T00:37:11Z"
  },
  {
    "school":"Tulane",
    "quality_z":1.149324166,
    "game_value_z":0.3367071705,
    "market_z":0.0,
    "talent_prior_z":-0.6736692773,
    "solver_rating":1681.3645189267,
    "power_score":0.7519194103,
    "power_rating":1620.3071056468,
    "rank":17,
    "conference":"American Athletic",
    "abbreviation":"TULN",
    "season":2025,
    "week":16,
    "as_of":"2026-06-19T00:37:11Z"
  },
  {
    "school":"Boise State",
    "quality_z":0.9121671297,
    "game_value_z":0.7597981136,
    "market_z":0.0,
    "talent_prior_z":-2.3865987631,
    "solver_rating":1689.5927582193,
    "power_score":0.7324094561,
    "power_rating":1617.1855129721,
    "rank":18,
    "conference":"Mountain West",
    "abbreviation":"BOIS",
    "season":2025,
    "week":16,
    "as_of":"2026-06-19T00:37:11Z"
  },
  {
    "school":"Penn State",
    "quality_z":1.0542262906,
    "game_value_z":0.4568702643,
    "market_z":0.0,
    "talent_prior_z":3.3977274784,
    "solver_rating":1721.4042432812,
    "power_score":0.7304666972,
    "power_rating":1616.8746715441,
    "rank":19,
    "conference":"Big Ten",
    "abbreviation":"PSU",
    "season":2025,
    "week":16,
    "as_of":"2026-06-19T00:37:11Z"
  },
  {
    "school":"North Texas",
    "quality_z":1.1592324999,
    "game_value_z":0.1536808203,
    "market_z":0.0,
    "talent_prior_z":-0.0590769596,
    "solver_rating":1763.8578627649,
    "power_score":0.7072001357,
    "power_rating":1613.1520217182,
    "rank":20,
    "conference":"American Athletic",
    "abbreviation":"UNT",
    "season":2025,
    "week":16,
    "as_of":"2026-06-19T00:37:11Z"
  },
  {
    "school":"Tennessee",
    "quality_z":0.5342980944,
    "game_value_z":1.3505935706,
    "market_z":0.0,
    "talent_prior_z":-2.4972563499,
    "solver_rating":1641.2479728825,
    "power_score":0.6783768185,
    "power_rating":1608.5402909574,
    "rank":21,
    "conference":"SEC",
    "abbreviation":"TENN",
    "season":2025,
    "week":16,
    "as_of":"2026-06-19T00:37:11Z"
  },
  {
    "school":"Old Dominion",
    "quality_z":1.5268108631,
    "game_value_z":-0.7978225777,
    "market_z":0.0,
    "talent_prior_z":0.193813783,
    "solver_rating":1714.2457604355,
    "power_score":0.6559979759,
    "power_rating":1604.9596761371,
    "rank":22,
    "conference":"Sun Belt",
    "abbreviation":"ODU",
    "season":2025,
    "week":16,
    "as_of":"2026-06-19T00:37:11Z"
  },
  {
    "school":"Oklahoma",
    "quality_z":0.3396177242,
    "game_value_z":1.5419560308,
    "market_z":0.0,
    "talent_prior_z":-0.5382182159,
    "solver_rating":1711.8303276543,
    "power_score":0.6194154913,
    "power_rating":1599.1064786077,
    "rank":23,
    "conference":"SEC",
    "abbreviation":"OU",
    "season":2025,
    "week":16,
    "as_of":"2026-06-19T00:37:11Z"
  },
  {
    "school":"Texas A&M",
    "quality_z":0.5339019781,
    "game_value_z":1.1343804318,
    "market_z":0.0,
    "talent_prior_z":-0.2139413861,
    "solver_rating":1745.0091481032,
    "power_score":0.6186083614,
    "power_rating":1598.9773378215,
    "rank":24,
    "conference":"SEC",
    "abbreviation":"TA&M",
    "season":2025,
    "week":16,
    "as_of":"2026-06-19T00:37:11Z"
  },
  {
    "school":"Clemson",
    "quality_z":0.7233464059,
    "game_value_z":0.7069559494,
    "market_z":0.0,
    "talent_prior_z":3.374682824,
    "solver_rating":1740.0706558186,
    "power_score":0.609559313,
    "power_rating":1597.5294900847,
    "rank":25,
    "conference":"ACC",
    "abbreviation":"CLEM",
    "season":2025,
    "week":16,
    "as_of":"2026-06-19T00:37:11Z"
  },
  {
    "school":"Iowa",
    "quality_z":0.6840141929,
    "game_value_z":0.7373399395,
    "market_z":0.0,
    "talent_prior_z":0.2769407731,
    "solver_rating":1767.2362863317,
    "power_score":0.595367488,
    "power_rating":1595.2587980879,
    "rank":26,
    "conference":"Big Ten",
    "abbreviation":"IOWA",
    "season":2025,
    "week":16,
    "as_of":"2026-06-19T00:37:11Z"
  },
  {
    "school":"Washington State",
    "quality_z":0.797267483,
    "game_value_z":0.4057409965,
    "market_z":0.0,
    "talent_prior_z":-0.61643127,
    "solver_rating":1726.6754951417,
    "power_score":0.5690075773,
    "power_rating":1591.0412123706,
    "rank":27,
    "conference":"Pac-12",
    "abbreviation":"WSU",
    "season":2025,
    "week":16,
    "as_of":"2026-06-19T00:37:11Z"
  },
  {
    "school":"Arizona",
    "quality_z":1.0215260807,
    "game_value_z":-0.0647194398,
    "market_z":0.0,
    "talent_prior_z":-0.002588091,
    "solver_rating":1706.9091458952,
    "power_score":0.5680748985,
    "power_rating":1590.8919837625,
    "rank":28,
    "conference":"Big 12",
    "abbreviation":"ARIZ",
    "season":2025,
    "week":16,
    "as_of":"2026-06-19T00:37:11Z"
  },
  {
    "school":"UNLV",
    "quality_z":0.7752192404,
    "game_value_z":0.4088302561,
    "market_z":0.0,
    "talent_prior_z":-0.7673323851,
    "solver_rating":1651.9844386563,
    "power_score":0.5572125091,
    "power_rating":1589.1540014618,
    "rank":29,
    "conference":"Mountain West",
    "abbreviation":"UNLV",
    "season":2025,
    "week":16,
    "as_of":"2026-06-19T00:37:11Z"
  },
  {
    "school":"BYU",
    "quality_z":0.2248496459,
    "game_value_z":1.4750041699,
    "market_z":0.0,
    "talent_prior_z":0.9263707172,
    "solver_rating":1718.1783552801,
    "power_score":0.5351527699,
    "power_rating":1585.6244431831,
    "rank":30,
    "conference":"Big 12",
    "abbreviation":"BYU",
    "season":2025,
    "week":16,
    "as_of":"2026-06-19T00:37:11Z"
  },
  {
    "school":"Virginia",
    "quality_z":0.4419363782,
    "game_value_z":1.0012494291,
    "market_z":0.0,
    "talent_prior_z":-0.6131864725,
    "solver_rating":1646.0705282873,
    "power_score":0.5291994662,
    "power_rating":1584.6719145941,
    "rank":31,
    "conference":"ACC",
    "abbreviation":"UVA",
    "season":2025,
    "week":16,
    "as_of":"2026-06-19T00:37:11Z"
  },
  {
    "school":"Louisville",
    "quality_z":0.3134736719,
    "game_value_z":1.1883891849,
    "market_z":0.0,
    "talent_prior_z":0.2728756725,
    "solver_rating":1675.3115886298,
    "power_score":0.5070545001,
    "power_rating":1581.1287200081,
    "rank":32,
    "conference":"ACC",
    "abbreviation":"LOU",
    "season":2025,
    "week":16,
    "as_of":"2026-06-19T00:37:11Z"
  },
  {
    "school":"UTSA",
    "quality_z":0.7308887738,
    "game_value_z":0.2385513489,
    "market_z":0.0,
    "talent_prior_z":1.0529394271,
    "solver_rating":1646.5628450832,
    "power_score":0.4848949265,
    "power_rating":1577.5831882476,
    "rank":33,
    "conference":"American Athletic",
    "abbreviation":"UTSA",
    "season":2025,
    "week":16,
    "as_of":"2026-06-19T00:37:11Z"
  },
  {
    "school":"Iowa State",
    "quality_z":0.761858824,
    "game_value_z":0.1247953526,
    "market_z":0.0,
    "talent_prior_z":-1.7239484142,
    "solver_rating":1560.0950436575,
    "power_score":0.4713314512,
    "power_rating":1575.4130321914,
    "rank":34,
    "conference":"Big 12",
    "abbreviation":"ISU",
    "season":2025,
    "week":16,
    "as_of":"2026-06-19T00:37:11Z"
  },
  {
    "school":"USC",
    "quality_z":0.3451976811,
    "game_value_z":0.9921750013,
    "market_z":0.0,
    "talent_prior_z":0.1952865388,
    "solver_rating":1717.7799199658,
    "power_score":0.4712159362,
    "power_rating":1575.3945497971,
    "rank":35,
    "conference":"Big Ten",
    "abbreviation":"USC",
    "season":2025,
    "week":16,
    "as_of":"2026-06-19T00:37:11Z"
  },
  {
    "school":"Kansas State",
    "quality_z":0.501880714,
    "game_value_z":0.6144618813,
    "market_z":0.0,
    "talent_prior_z":-0.2832542337,
    "solver_rating":1571.3688641509,
    "power_score":0.457066179,
    "power_rating":1573.1305886396,
    "rank":36,
    "conference":"Big 12",
    "abbreviation":"KSU",
    "season":2025,
    "week":16,
    "as_of":"2026-06-19T00:37:11Z"
  },
  {
    "school":"Duke",
    "quality_z":0.3650255821,
    "game_value_z":0.8313519623,
    "market_z":0.0,
    "talent_prior_z":-0.7317114255,
    "solver_rating":1637.4755544861,
    "power_score":0.4383004392,
    "power_rating":1570.1280702753,
    "rank":37,
    "conference":"ACC",
    "abbreviation":"DUKE",
    "season":2025,
    "week":16,
    "as_of":"2026-06-19T00:37:11Z"
  },
  {
    "school":"Wake Forest",
    "quality_z":0.5733517249,
    "game_value_z":0.3613516738,
    "market_z":0.0,
    "talent_prior_z":-0.6996638863,
    "solver_rating":1599.8585084201,
    "power_score":0.4283563987,
    "power_rating":1568.5370237965,
    "rank":38,
    "conference":"ACC",
    "abbreviation":"WAKE",
    "season":2025,
    "week":16,
    "as_of":"2026-06-19T00:37:11Z"
  },
  {
    "school":"East Carolina",
    "quality_z":0.6914015755,
    "game_value_z":0.0685382778,
    "market_z":0.0,
    "talent_prior_z":-0.1362586072,
    "solver_rating":1655.9485551254,
    "power_score":0.4154284127,
    "power_rating":1566.4685460336,
    "rank":39,
    "conference":"American Athletic",
    "abbreviation":"ECU",
    "season":2025,
    "week":16,
    "as_of":"2026-06-19T00:37:11Z"
  },
  {
    "school":"Texas State",
    "quality_z":1.2663174589,
    "game_value_z":-1.2246430086,
    "market_z":0.0,
    "talent_prior_z":0.90365213,
    "solver_rating":1590.1860819768,
    "power_score":0.3890529001,
    "power_rating":1562.2484640164,
    "rank":40,
    "conference":"Sun Belt",
    "abbreviation":"TXST",
    "season":2025,
    "week":16,
    "as_of":"2026-06-19T00:37:11Z"
  },
  {
    "school":"Navy",
    "quality_z":0.3584328418,
    "game_value_z":0.4945116683,
    "market_z":0.0,
    "talent_prior_z":0.1864113954,
    "solver_rating":1596.0001947569,
    "power_score":0.3417593217,
    "power_rating":1554.681491476,
    "rank":41,
    "conference":"American Athletic",
    "abbreviation":"NAVY",
    "season":2025,
    "week":16,
    "as_of":"2026-06-19T00:37:11Z"
  },
  {
    "school":"Texas",
    "quality_z":0.0526437054,
    "game_value_z":1.1221354497,
    "market_z":0.0,
    "talent_prior_z":3.051205794,
    "solver_rating":1682.1980729173,
    "power_score":0.3392100624,
    "power_rating":1554.2736099807,
    "rank":42,
    "conference":"SEC",
    "abbreviation":"TEX",
    "season":2025,
    "week":16,
    "as_of":"2026-06-19T00:37:11Z"
  },
  {
    "school":"New Mexico",
    "quality_z":0.5190665749,
    "game_value_z":0.0479067303,
    "market_z":0.0,
    "talent_prior_z":-1.3291317861,
    "solver_rating":1586.5359001523,
    "power_score":0.3109039082,
    "power_rating":1549.7446253138,
    "rank":43,
    "conference":"Mountain West",
    "abbreviation":"UNM",
    "season":2025,
    "week":16,
    "as_of":"2026-06-19T00:37:11Z"
  },
  {
    "school":"Michigan",
    "quality_z":0.1779041969,
    "game_value_z":0.7319690619,
    "market_z":0.0,
    "talent_prior_z":0.1409197682,
    "solver_rating":1629.8803750412,
    "power_score":0.3036084604,
    "power_rating":1548.577353666,
    "rank":44,
    "conference":"Big Ten",
    "abbreviation":"MICH",
    "season":2025,
    "week":16,
    "as_of":"2026-06-19T00:37:11Z"
  },
  {
    "school":"South Carolina",
    "quality_z":0.080415098,
    "game_value_z":0.856056602,
    "market_z":0.0,
    "talent_prior_z":0.7205348348,
    "solver_rating":1599.1131341544,
    "power_score":0.2818649812,
    "power_rating":1545.0983969854,
    "rank":45,
    "conference":"SEC",
    "abbreviation":"SC",
    "season":2025,
    "week":16,
    "as_of":"2026-06-19T00:37:11Z"
  },
  {
    "school":"Utah State",
    "quality_z":0.2798947064,
    "game_value_z":0.3452980531,
    "market_z":0.0,
    "talent_prior_z":0.0175143249,
    "solver_rating":1620.8732386355,
    "power_score":0.2556228983,
    "power_rating":1540.8996637314,
    "rank":46,
    "conference":"Mountain West",
    "abbreviation":"USU",
    "season":2025,
    "week":16,
    "as_of":"2026-06-19T00:37:11Z"
  },
  {
    "school":"Alabama",
    "quality_z":-0.1594166696,
    "game_value_z":1.2361471803,
    "market_z":0.0,
    "talent_prior_z":1.8618596163,
    "solver_rating":1691.0529357206,
    "power_score":0.2489793937,
    "power_rating":1539.8367029987,
    "rank":47,
    "conference":"SEC",
    "abbreviation":"ALA",
    "season":2025,
    "week":16,
    "as_of":"2026-06-19T00:37:11Z"
  },
  {
    "school":"Western Michigan",
    "quality_z":0.7736057061,
    "game_value_z":-0.754239894,
    "market_z":0.0,
    "talent_prior_z":0.7792244222,
    "solver_rating":1620.1502289952,
    "power_score":0.2359981708,
    "power_rating":1537.7597073278,
    "rank":48,
    "conference":"Mid-American",
    "abbreviation":"WMU",
    "season":2025,
    "week":16,
    "as_of":"2026-06-19T00:37:11Z"
  },
  {
    "school":"Illinois",
    "quality_z":0.212507608,
    "game_value_z":0.3638298428,
    "market_z":0.0,
    "talent_prior_z":0.3625732083,
    "solver_rating":1530.4232217471,
    "power_score":0.222076275,
    "power_rating":1535.5322040069,
    "rank":49,
    "conference":"Big Ten",
    "abbreviation":"ILL",
    "season":2025,
    "week":16,
    "as_of":"2026-06-19T00:37:11Z"
  },
  {
    "school":"Florida State",
    "quality_z":-0.0392728062,
    "game_value_z":0.8847165225,
    "market_z":0.0,
    "talent_prior_z":-0.6382057682,
    "solver_rating":1552.0096881471,
    "power_score":0.2211102769,
    "power_rating":1535.3776442998,
    "rank":50,
    "conference":"ACC",
    "abbreviation":"FSU",
    "season":2025,
    "week":16,
    "as_of":"2026-06-19T00:37:11Z"
  },
  {
    "school":"NC State",
    "quality_z":0.0483065805,
    "game_value_z":0.6331961474,
    "market_z":0.0,
    "talent_prior_z":1.0977671687,
    "solver_rating":1584.8638397863,
    "power_score":0.2020772861,
    "power_rating":1532.33236578,
    "rank":51,
    "conference":"ACC",
    "abbreviation":"NCSU",
    "season":2025,
    "week":16,
    "as_of":"2026-06-19T00:37:11Z"
  },
  {
    "school":"TCU",
    "quality_z":0.2370523138,
    "game_value_z":0.1652162717,
    "market_z":0.0,
    "talent_prior_z":0.5451135479,
    "solver_rating":1548.3811733911,
    "power_score":0.1814592646,
    "power_rating":1529.0334823406,
    "rank":52,
    "conference":"Big 12",
    "abbreviation":"TCU",
    "season":2025,
    "week":16,
    "as_of":"2026-06-19T00:37:11Z"
  },
  {
    "school":"LSU",
    "quality_z":-0.2126464769,
    "game_value_z":1.0986237604,
    "market_z":0.0,
    "talent_prior_z":1.8650264715,
    "solver_rating":1561.3839677396,
    "power_score":0.1805778642,
    "power_rating":1528.8924582679,
    "rank":53,
    "conference":"SEC",
    "abbreviation":"LSU",
    "season":2025,
    "week":16,
    "as_of":"2026-06-19T00:37:11Z"
  },
  {
    "school":"Florida",
    "quality_z":-0.431431073,
    "game_value_z":1.4864818784,
    "market_z":0.0,
    "talent_prior_z":0.2022960673,
    "solver_rating":1487.7985464496,
    "power_score":0.1619029494,
    "power_rating":1525.9044719074,
    "rank":54,
    "conference":"SEC",
    "abbreviation":"FLA",
    "season":2025,
    "week":16,
    "as_of":"2026-06-19T00:37:11Z"
  },
  {
    "school":"Auburn",
    "quality_z":-0.2640550127,
    "game_value_z":1.0988026383,
    "market_z":0.0,
    "talent_prior_z":-0.3082172415,
    "solver_rating":1590.9555276767,
    "power_score":0.1511416979,
    "power_rating":1524.1826716567,
    "rank":55,
    "conference":"SEC",
    "abbreviation":"AUB",
    "season":2025,
    "week":16,
    "as_of":"2026-06-19T00:37:11Z"
  },
  {
    "school":"San Diego State",
    "quality_z":0.4121486315,
    "game_value_z":-0.3915641994,
    "market_z":0.0,
    "talent_prior_z":0.3913842406,
    "solver_rating":1590.7460992364,
    "power_score":0.1285584955,
    "power_rating":1520.5693592734,
    "rank":56,
    "conference":"Mountain West",
    "abbreviation":"SDSU",
    "season":2025,
    "week":16,
    "as_of":"2026-06-19T00:37:11Z"
  },
  {
    "school":"UConn",
    "quality_z":0.4282586771,
    "game_value_z":-0.4927103087,
    "market_z":0.0,
    "talent_prior_z":0.1761813525,
    "solver_rating":1540.3960206783,
    "power_score":0.1099445863,
    "power_rating":1517.5911338016,
    "rank":57,
    "conference":"FBS Independents",
    "abbreviation":"CONN",
    "season":2025,
    "week":16,
    "as_of":"2026-06-19T00:37:11Z"
  },
  {
    "school":"Arizona State",
    "quality_z":0.1536531992,
    "game_value_z":-0.0515550486,
    "market_z":0.0,
    "talent_prior_z":1.2633283995,
    "solver_rating":1521.8185611168,
    "power_score":0.0739306269,
    "power_rating":1511.8289003018,
    "rank":58,
    "conference":"Big 12",
    "abbreviation":"ASU",
    "season":2025,
    "week":16,
    "as_of":"2026-06-19T00:37:11Z"
  },
  {
    "school":"Fresno State",
    "quality_z":0.4007665026,
    "game_value_z":-0.5701057453,
    "market_z":0.0,
    "talent_prior_z":-0.8866941658,
    "solver_rating":1550.2664943845,
    "power_score":0.0728630865,
    "power_rating":1511.6580938461,
    "rank":59,
    "conference":"Mountain West",
    "abbreviation":"FRES",
    "season":2025,
    "week":16,
    "as_of":"2026-06-19T00:37:11Z"
  },
  {
    "school":"California",
    "quality_z":-0.3529514874,
    "game_value_z":0.9983072646,
    "market_z":0.0,
    "talent_prior_z":-0.5428278875,
    "solver_rating":1456.8684410395,
    "power_score":0.0724803765,
    "power_rating":1511.596860239,
    "rank":60,
    "conference":"ACC",
    "abbreviation":"CAL",
    "season":2025,
    "week":16,
    "as_of":"2026-06-19T00:37:11Z"
  },
  {
    "school":"Georgia Tech",
    "quality_z":-0.0781668766,
    "game_value_z":0.3965092853,
    "market_z":0.0,
    "talent_prior_z":0.8023226621,
    "solver_rating":1546.6680485757,
    "power_score":0.0643589217,
    "power_rating":1510.2974274672,
    "rank":61,
    "conference":"ACC",
    "abbreviation":"GT",
    "season":2025,
    "week":16,
    "as_of":"2026-06-19T00:37:11Z"
  },
  {
    "school":"Miami (OH)",
    "quality_z":0.3433967075,
    "game_value_z":-0.5638783547,
    "market_z":0.0,
    "talent_prior_z":-0.2331316828,
    "solver_rating":1539.1838396415,
    "power_score":0.0416734861,
    "power_rating":1506.6677577701,
    "rank":62,
    "conference":"Mid-American",
    "abbreviation":"M-OH",
    "season":2025,
    "week":16,
    "as_of":"2026-06-19T00:37:11Z"
  },
  {
    "school":"Florida International",
    "quality_z":0.7911426007,
    "game_value_z":-1.5140287485,
    "market_z":0.0,
    "talent_prior_z":-0.5531334852,
    "solver_rating":1602.9692004436,
    "power_score":0.0368241007,
    "power_rating":1505.8918561052,
    "rank":63,
    "conference":"Conference USA",
    "abbreviation":"FIU",
    "season":2025,
    "week":16,
    "as_of":"2026-06-19T00:37:11Z"
  },
  {
    "school":"Hawai'i",
    "quality_z":0.3036660854,
    "game_value_z":-0.5244363512,
    "market_z":0.0,
    "talent_prior_z":-0.5937341708,
    "solver_rating":1531.6693160849,
    "power_score":0.0297475694,
    "power_rating":1504.7596110965,
    "rank":64,
    "conference":"Mountain West",
    "abbreviation":"HAW",
    "season":2025,
    "week":16,
    "as_of":"2026-06-19T00:37:11Z"
  },
  {
    "school":"Ohio",
    "quality_z":0.7187555672,
    "game_value_z":-1.405274894,
    "market_z":0.0,
    "talent_prior_z":0.1803604185,
    "solver_rating":1511.6743703431,
    "power_score":0.0252553154,
    "power_rating":1504.0408504649,
    "rank":65,
    "conference":"Mid-American",
    "abbreviation":"OHIO",
    "season":2025,
    "week":16,
    "as_of":"2026-06-19T00:37:11Z"
  },
  {
    "school":"Houston",
    "quality_z":0.1660134979,
    "game_value_z":-0.3061253964,
    "market_z":0.0,
    "talent_prior_z":1.0751806229,
    "solver_rating":1512.2248231792,
    "power_score":0.0109157314,
    "power_rating":1501.7465170305,
    "rank":66,
    "conference":"Big 12",
    "abbreviation":"HOU",
    "season":2025,
    "week":16,
    "as_of":"2026-06-19T00:37:11Z"
  },
  {
    "school":"Arkansas",
    "quality_z":-0.5383507814,
    "game_value_z":1.1415669937,
    "market_z":0.0,
    "talent_prior_z":-0.0617755735,
    "solver_rating":1438.4146479133,
    "power_score":0.0055955823,
    "power_rating":1500.8952931756,
    "rank":67,
    "conference":"SEC",
    "abbreviation":"ARK",
    "season":2025,
    "week":16,
    "as_of":"2026-06-19T00:37:11Z"
  },
  {
    "school":"Army",
    "quality_z":-0.0518616611,
    "game_value_z":0.082662174,
    "market_z":0.0,
    "talent_prior_z":-1.3663383109,
    "solver_rating":1515.2991573352,
    "power_score":-0.0069816199,
    "power_rating":1498.882940822,
    "rank":68,
    "conference":"American Athletic",
    "abbreviation":"ARMY",
    "season":2025,
    "week":16,
    "as_of":"2026-06-19T00:37:11Z"
  },
  {
    "school":"Kennesaw State",
    "quality_z":0.472696936,
    "game_value_z":-1.0924420974,
    "market_z":0.0,
    "talent_prior_z":-0.9027176069,
    "solver_rating":1594.8464193619,
    "power_score":-0.0297232973,
    "power_rating":1495.2442724389,
    "rank":69,
    "conference":"Conference USA",
    "abbreviation":"KENN",
    "season":2025,
    "week":16,
    "as_of":"2026-06-19T00:37:11Z"
  },
  {
    "school":"Western Kentucky",
    "quality_z":0.3517468004,
    "game_value_z":-0.8637816266,
    "market_z":0.0,
    "talent_prior_z":-0.6913893316,
    "solver_rating":1535.8132570432,
    "power_score":-0.0361253511,
    "power_rating":1494.2199438306,
    "rank":70,
    "conference":"Conference USA",
    "abbreviation":"WKU",
    "season":2025,
    "week":16,
    "as_of":"2026-06-19T00:37:11Z"
  },
  {
    "school":"Boston College",
    "quality_z":-0.1654787305,
    "game_value_z":0.2113487169,
    "market_z":0.0,
    "talent_prior_z":0.288484067,
    "solver_rating":1398.6380108777,
    "power_score":-0.0367088318,
    "power_rating":1494.1265869182,
    "rank":71,
    "conference":"ACC",
    "abbreviation":"BC",
    "season":2025,
    "week":16,
    "as_of":"2026-06-19T00:37:11Z"
  },
  {
    "school":"Stanford",
    "quality_z":-0.4981423622,
    "game_value_z":0.8840556466,
    "market_z":0.0,
    "talent_prior_z":-0.8828183262,
    "solver_rating":1445.7685042789,
    "power_score":-0.0422568899,
    "power_rating":1493.2388976109,
    "rank":72,
    "conference":"ACC",
    "abbreviation":"STAN",
    "season":2025,
    "week":16,
    "as_of":"2026-06-19T00:37:11Z"
  },
  {
    "school":"Michigan State",
    "quality_z":-0.1985935543,
    "game_value_z":0.2407864899,
    "market_z":0.0,
    "talent_prior_z":0.3480988575,
    "solver_rating":1454.8374498459,
    "power_score":-0.0475952373,
    "power_rating":1492.3847620399,
    "rank":73,
    "conference":"Big Ten",
    "abbreviation":"MSU",
    "season":2025,
    "week":16,
    "as_of":"2026-06-19T00:37:11Z"
  },
  {
    "school":"Central Michigan",
    "quality_z":0.3273555452,
    "game_value_z":-0.8971588834,
    "market_z":0.0,
    "talent_prior_z":-1.4901250841,
    "solver_rating":1507.7786003093,
    "power_score":-0.0593064888,
    "power_rating":1490.5109617913,
    "rank":74,
    "conference":"Mid-American",
    "abbreviation":"CMU",
    "season":2025,
    "week":16,
    "as_of":"2026-06-19T00:37:11Z"
  },
  {
    "school":"Northwestern",
    "quality_z":-0.261961453,
    "game_value_z":0.3007209101,
    "market_z":0.0,
    "talent_prior_z":0.3425471827,
    "solver_rating":1501.4833250126,
    "power_score":-0.0674350936,
    "power_rating":1489.2103850248,
    "rank":75,
    "conference":"Big Ten",
    "abbreviation":"NU",
    "season":2025,
    "week":16,
    "as_of":"2026-06-19T00:37:11Z"
  },
  {
    "school":"Wisconsin",
    "quality_z":-0.6339841576,
    "game_value_z":0.9626957482,
    "market_z":0.0,
    "talent_prior_z":-0.0256537774,
    "solver_rating":1514.0468534384,
    "power_score":-0.098513022,
    "power_rating":1484.2379164778,
    "rank":76,
    "conference":"Big Ten",
    "abbreviation":"WIS",
    "season":2025,
    "week":16,
    "as_of":"2026-06-19T00:37:11Z"
  },
  {
    "school":"Pittsburgh",
    "quality_z":-0.5933888189,
    "game_value_z":0.8150491432,
    "market_z":0.0,
    "talent_prior_z":0.5990928897,
    "solver_rating":1621.4202577051,
    "power_score":-0.1158887745,
    "power_rating":1481.4577960843,
    "rank":77,
    "conference":"ACC",
    "abbreviation":"PITT",
    "season":2025,
    "week":16,
    "as_of":"2026-06-19T00:37:11Z"
  },
  {
    "school":"Louisiana Tech",
    "quality_z":0.2048741445,
    "game_value_z":-0.9860231773,
    "market_z":0.0,
    "talent_prior_z":-0.2080030157,
    "solver_rating":1554.0914802719,
    "power_score":-0.1540274908,
    "power_rating":1475.3556014756,
    "rank":78,
    "conference":"Conference USA",
    "abbreviation":"LT",
    "season":2025,
    "week":16,
    "as_of":"2026-06-19T00:37:11Z"
  },
  {
    "school":"Eastern Michigan",
    "quality_z":0.2093381276,
    "game_value_z":-1.0542141239,
    "market_z":0.0,
    "talent_prior_z":-1.0441817079,
    "solver_rating":1392.3852489332,
    "power_score":-0.1702457455,
    "power_rating":1472.7606807257,
    "rank":79,
    "conference":"Mid-American",
    "abbreviation":"EMU",
    "season":2025,
    "week":16,
    "as_of":"2026-06-19T00:37:11Z"
  },
  {
    "school":"Marshall",
    "quality_z":0.2605237924,
    "game_value_z":-1.2303492176,
    "market_z":0.0,
    "talent_prior_z":1.1208219892,
    "solver_rating":1421.2089723741,
    "power_score":-0.1893926285,
    "power_rating":1469.6971794382,
    "rank":80,
    "conference":"Sun Belt",
    "abbreviation":"MRSH",
    "season":2025,
    "week":16,
    "as_of":"2026-06-19T00:37:11Z"
  },
  {
    "school":"Air Force",
    "quality_z":-0.1460443728,
    "game_value_z":-0.4133123978,
    "market_z":0.0,
    "talent_prior_z":-0.7149025231,
    "solver_rating":1446.1632878307,
    "power_score":-0.1975828265,
    "power_rating":1468.3867477546,
    "rank":81,
    "conference":"Mountain West",
    "abbreviation":"AF",
    "season":2025,
    "week":16,
    "as_of":"2026-06-19T00:37:11Z"
  },
  {
    "school":"Troy",
    "quality_z":-0.0457564829,
    "game_value_z":-0.7144739861,
    "market_z":0.0,
    "talent_prior_z":-0.6342505223,
    "solver_rating":1502.0324496972,
    "power_score":-0.2229971501,
    "power_rating":1464.3204559899,
    "rank":82,
    "conference":"Sun Belt",
    "abbreviation":"TROY",
    "season":2025,
    "week":16,
    "as_of":"2026-06-19T00:37:11Z"
  },
  {
    "school":"Kentucky",
    "quality_z":-1.0313790123,
    "game_value_z":1.2740741245,
    "market_z":0.0,
    "talent_prior_z":-0.3447049173,
    "solver_rating":1455.4440030354,
    "power_score":-0.2406912251,
    "power_rating":1461.4894039792,
    "rank":83,
    "conference":"SEC",
    "abbreviation":"UK",
    "season":2025,
    "week":16,
    "as_of":"2026-06-19T00:37:11Z"
  },
  {
    "school":"Minnesota",
    "quality_z":-0.7223611526,
    "game_value_z":0.5998091634,
    "market_z":0.0,
    "talent_prior_z":0.0673581658,
    "solver_rating":1451.3972285643,
    "power_score":-0.2491342815,
    "power_rating":1460.1385149562,
    "rank":84,
    "conference":"Big Ten",
    "abbreviation":"MINN",
    "season":2025,
    "week":16,
    "as_of":"2026-06-19T00:37:11Z"
  },
  {
    "school":"Cincinnati",
    "quality_z":-0.5443661044,
    "game_value_z":0.2219898127,
    "market_z":0.0,
    "talent_prior_z":0.6339360834,
    "solver_rating":1450.164807177,
    "power_score":-0.2510897614,
    "power_rating":1459.8256381744,
    "rank":85,
    "conference":"Big 12",
    "abbreviation":"CIN",
    "season":2025,
    "week":16,
    "as_of":"2026-06-19T00:37:11Z"
  },
  {
    "school":"Memphis",
    "quality_z":-0.5840301358,
    "game_value_z":0.2682886638,
    "market_z":0.0,
    "talent_prior_z":-0.7773371567,
    "solver_rating":1564.3447522328,
    "power_score":-0.2610892307,
    "power_rating":1458.2257230913,
    "rank":86,
    "conference":"American Athletic",
    "abbreviation":"MEM",
    "season":2025,
    "week":16,
    "as_of":"2026-06-19T00:37:11Z"
  },
  {
    "school":"Kansas",
    "quality_z":-0.7825403746,
    "game_value_z":0.6144836064,
    "market_z":0.0,
    "talent_prior_z":-0.0557830213,
    "solver_rating":1447.9927495532,
    "power_score":-0.2796090637,
    "power_rating":1455.2625498137,
    "rank":87,
    "conference":"Big 12",
    "abbreviation":"KU",
    "season":2025,
    "week":16,
    "as_of":"2026-06-19T00:37:11Z"
  },
  {
    "school":"Tulsa",
    "quality_z":-0.0906948476,
    "game_value_z":-0.8487719104,
    "market_z":0.0,
    "talent_prior_z":0.4081938057,
    "solver_rating":1314.1401837645,
    "power_score":-0.2857548687,
    "power_rating":1454.2792210015,
    "rank":88,
    "conference":"American Athletic",
    "abbreviation":"TLSA",
    "season":2025,
    "week":16,
    "as_of":"2026-06-19T00:37:11Z"
  },
  {
    "school":"North Carolina",
    "quality_z":-0.7013971404,
    "game_value_z":0.3885189245,
    "market_z":0.0,
    "talent_prior_z":-0.5878090267,
    "solver_rating":1369.4524745384,
    "power_score":-0.2952959325,
    "power_rating":1452.7526507946,
    "rank":89,
    "conference":"ACC",
    "abbreviation":"UNC",
    "season":2025,
    "week":16,
    "as_of":"2026-06-19T00:37:11Z"
  },
  {
    "school":"Nevada",
    "quality_z":-0.301880063,
    "game_value_z":-0.4536519128,
    "market_z":0.0,
    "talent_prior_z":-0.0830582864,
    "solver_rating":1349.2208792838,
    "power_score":-0.2980713569,
    "power_rating":1452.3085829001,
    "rank":90,
    "conference":"Mountain West",
    "abbreviation":"NEV",
    "season":2025,
    "week":16,
    "as_of":"2026-06-19T00:37:11Z"
  },
  {
    "school":"Rutgers",
    "quality_z":-0.760566723,
    "game_value_z":0.4435120347,
    "market_z":0.0,
    "talent_prior_z":0.4203446205,
    "solver_rating":1425.159625766,
    "power_score":-0.3140885889,
    "power_rating":1449.745825784,
    "rank":91,
    "conference":"Big Ten",
    "abbreviation":"RUTG",
    "season":2025,
    "week":16,
    "as_of":"2026-06-19T00:37:11Z"
  },
  {
    "school":"Virginia Tech",
    "quality_z":-1.0134784197,
    "game_value_z":0.8582817488,
    "market_z":0.0,
    "talent_prior_z":0.151762959,
    "solver_rating":1396.7161167166,
    "power_score":-0.3449261659,
    "power_rating":1444.8118134491,
    "rank":92,
    "conference":"ACC",
    "abbreviation":"VT",
    "season":2025,
    "week":16,
    "as_of":"2026-06-19T00:37:11Z"
  },
  {
    "school":"UCF",
    "quality_z":-0.8348521559,
    "game_value_z":0.4013894811,
    "market_z":0.0,
    "talent_prior_z":-0.2664764526,
    "solver_rating":1360.774056795,
    "power_score":-0.3682948905,
    "power_rating":1441.0728175226,
    "rank":93,
    "conference":"Big 12",
    "abbreviation":"UCF",
    "season":2025,
    "week":16,
    "as_of":"2026-06-19T00:37:11Z"
  },
  {
    "school":"Kent State",
    "quality_z":-0.0290839652,
    "game_value_z":-1.3098505122,
    "market_z":0.0,
    "talent_prior_z":-1.7863936496,
    "solver_rating":1320.0698937424,
    "power_score":-0.377390745,
    "power_rating":1439.617480798,
    "rank":94,
    "conference":"Mid-American",
    "abbreviation":"KENT",
    "season":2025,
    "week":16,
    "as_of":"2026-06-19T00:37:11Z"
  },
  {
    "school":"Jacksonville State",
    "quality_z":-0.0871174511,
    "game_value_z":-1.2459047446,
    "market_z":0.0,
    "talent_prior_z":0.6285404547,
    "solver_rating":1496.783021738,
    "power_score":-0.3930663887,
    "power_rating":1437.1093778093,
    "rank":95,
    "conference":"Conference USA",
    "abbreviation":"JXST",
    "season":2025,
    "week":16,
    "as_of":"2026-06-19T00:37:11Z"
  },
  {
    "school":"Mississippi State",
    "quality_z":-1.3285057167,
    "game_value_z":1.3256076066,
    "market_z":0.0,
    "talent_prior_z":-0.1806054178,
    "solver_rating":1408.5517408322,
    "power_score":-0.3969171886,
    "power_rating":1436.4932498178,
    "rank":96,
    "conference":"SEC",
    "abbreviation":"MSST",
    "season":2025,
    "week":16,
    "as_of":"2026-06-19T00:37:11Z"
  },
  {
    "school":"Akron",
    "quality_z":0.3558528772,
    "game_value_z":-2.184126585,
    "market_z":0.0,
    "talent_prior_z":-0.7729855527,
    "solver_rating":1336.5633440329,
    "power_score":-0.3973698929,
    "power_rating":1436.4208171425,
    "rank":97,
    "conference":"Mid-American",
    "abbreviation":"AKR",
    "season":2025,
    "week":16,
    "as_of":"2026-06-19T00:37:11Z"
  },
  {
    "school":"Arkansas State",
    "quality_z":-0.1119665278,
    "game_value_z":-1.3809544046,
    "market_z":0.0,
    "talent_prior_z":-0.1181651597,
    "solver_rating":1406.9490848085,
    "power_score":-0.4445088873,
    "power_rating":1428.8785780348,
    "rank":98,
    "conference":"Sun Belt",
    "abbreviation":"ARST",
    "season":2025,
    "week":16,
    "as_of":"2026-06-19T00:37:11Z"
  },
  {
    "school":"Middle Tennessee",
    "quality_z":0.195871416,
    "game_value_z":-2.0281345572,
    "market_z":0.0,
    "talent_prior_z":0.5574754526,
    "solver_rating":1338.0087597491,
    "power_score":-0.4461700098,
    "power_rating":1428.6127984258,
    "rank":99,
    "conference":"Conference USA",
    "abbreviation":"MTSU",
    "season":2025,
    "week":16,
    "as_of":"2026-06-19T00:37:11Z"
  },
  {
    "school":"West Virginia",
    "quality_z":-0.990831362,
    "game_value_z":0.3951459856,
    "market_z":0.0,
    "talent_prior_z":-0.5451946523,
    "solver_rating":1316.8679022831,
    "power_score":-0.4594762955,
    "power_rating":1426.4837927276,
    "rank":100,
    "conference":"Big 12",
    "abbreviation":"WVU",
    "season":2025,
    "week":16,
    "as_of":"2026-06-19T00:37:11Z"
  },
  {
    "school":"Delaware",
    "quality_z":0.0327749619,
    "game_value_z":-1.8145068005,
    "market_z":0.0,
    "talent_prior_z":0.0,
    "solver_rating":1337.495215744,
    "power_score":-0.4808848771,
    "power_rating":1423.0584196663,
    "rank":101,
    "conference":"Conference USA",
    "abbreviation":"DEL",
    "season":2025,
    "week":16,
    "as_of":"2026-06-19T00:37:11Z"
  },
  {
    "school":"Liberty",
    "quality_z":-0.2660359074,
    "game_value_z":-1.2265171865,
    "market_z":0.0,
    "talent_prior_z":0.9917433291,
    "solver_rating":1487.2977126533,
    "power_score":-0.4903462899,
    "power_rating":1421.5445936083,
    "rank":102,
    "conference":"Conference USA",
    "abbreviation":"LIB",
    "season":2025,
    "week":16,
    "as_of":"2026-06-19T00:37:11Z"
  },
  {
    "school":"Oklahoma State",
    "quality_z":-0.8801798209,
    "game_value_z":0.0515736829,
    "market_z":0.0,
    "talent_prior_z":-0.2882287826,
    "solver_rating":1247.7177384707,
    "power_score":-0.4906256933,
    "power_rating":1421.499889068,
    "rank":103,
    "conference":"Big 12",
    "abbreviation":"OKST",
    "season":2025,
    "week":16,
    "as_of":"2026-06-19T00:37:11Z"
  },
  {
    "school":"Missouri State",
    "quality_z":-0.2317031336,
    "game_value_z":-1.3033538657,
    "market_z":0.0,
    "talent_prior_z":0.0,
    "solver_rating":1465.6530871899,
    "power_score":-0.491814146,
    "power_rating":1421.3097366394,
    "rank":104,
    "conference":"Conference USA",
    "abbreviation":"MOST",
    "season":2025,
    "week":16,
    "as_of":"2026-06-19T00:37:11Z"
  },
  {
    "school":"Louisiana",
    "quality_z":-0.2055234632,
    "game_value_z":-1.4592358634,
    "market_z":0.0,
    "talent_prior_z":-0.0221183877,
    "solver_rating":1428.3098222202,
    "power_score":-0.5197259031,
    "power_rating":1416.8438555017,
    "rank":105,
    "conference":"Sun Belt",
    "abbreviation":"UL",
    "season":2025,
    "week":16,
    "as_of":"2026-06-19T00:37:11Z"
  },
  {
    "school":"Bowling Green",
    "quality_z":0.1479961063,
    "game_value_z":-2.2550933745,
    "market_z":0.0,
    "talent_prior_z":-1.2493087647,
    "solver_rating":1336.9828443644,
    "power_score":-0.5361293835,
    "power_rating":1414.2192986431,
    "rank":106,
    "conference":"Mid-American",
    "abbreviation":"BGSU",
    "season":2025,
    "week":16,
    "as_of":"2026-06-19T00:37:11Z"
  },
  {
    "school":"Nebraska",
    "quality_z":-1.0387798008,
    "game_value_z":0.211411299,
    "market_z":0.0,
    "talent_prior_z":0.4192942961,
    "solver_rating":1406.3068204653,
    "power_score":-0.5375744533,
    "power_rating":1413.9880874708,
    "rank":107,
    "conference":"Big Ten",
    "abbreviation":"NEB",
    "season":2025,
    "week":16,
    "as_of":"2026-06-19T00:37:11Z"
  },
  {
    "school":"Baylor",
    "quality_z":-0.8844399348,
    "game_value_z":-0.1934095713,
    "market_z":0.0,
    "talent_prior_z":0.9245116167,
    "solver_rating":1390.0547715427,
    "power_score":-0.5605331304,
    "power_rating":1410.3146991336,
    "rank":108,
    "conference":"Big 12",
    "abbreviation":"BAY",
    "season":2025,
    "week":16,
    "as_of":"2026-06-19T00:37:11Z"
  },
  {
    "school":"South Alabama",
    "quality_z":-0.3485314149,
    "game_value_z":-1.3780075515,
    "market_z":0.0,
    "talent_prior_z":-0.6422122375,
    "solver_rating":1371.6438604605,
    "power_score":-0.5793794453,
    "power_rating":1407.2992887542,
    "rank":109,
    "conference":"Sun Belt",
    "abbreviation":"USA",
    "season":2025,
    "week":16,
    "as_of":"2026-06-19T00:37:11Z"
  },
  {
    "school":"Georgia Southern",
    "quality_z":-0.401163712,
    "game_value_z":-1.2942268184,
    "market_z":0.0,
    "talent_prior_z":0.7122953894,
    "solver_rating":1351.896577521,
    "power_score":-0.5864950331,
    "power_rating":1406.160794712,
    "rank":110,
    "conference":"Sun Belt",
    "abbreviation":"GASO",
    "season":2025,
    "week":16,
    "as_of":"2026-06-19T00:37:11Z"
  },
  {
    "school":"Maryland",
    "quality_z":-1.0610830869,
    "game_value_z":0.0558515328,
    "market_z":0.0,
    "talent_prior_z":-0.8690251952,
    "solver_rating":1263.6696094043,
    "power_score":-0.5932049302,
    "power_rating":1405.0872111643,
    "rank":111,
    "conference":"Big Ten",
    "abbreviation":"MD",
    "season":2025,
    "week":16,
    "as_of":"2026-06-19T00:37:11Z"
  },
  {
    "school":"Florida Atlantic",
    "quality_z":-0.8977231867,
    "game_value_z":-0.3438673504,
    "market_z":0.0,
    "talent_prior_z":-0.9857166922,
    "solver_rating":1314.481248979,
    "power_score":-0.6095851594,
    "power_rating":1402.4663745015,
    "rank":112,
    "conference":"American Athletic",
    "abbreviation":"FAU",
    "season":2025,
    "week":16,
    "as_of":"2026-06-19T00:37:11Z"
  },
  {
    "school":"Oregon State",
    "quality_z":-0.8736674147,
    "game_value_z":-0.4121991678,
    "market_z":0.0,
    "talent_prior_z":-0.1136553634,
    "solver_rating":1302.0111758134,
    "power_score":-0.6146053138,
    "power_rating":1401.6631497928,
    "rank":113,
    "conference":"Pac-12",
    "abbreviation":"ORST",
    "season":2025,
    "week":16,
    "as_of":"2026-06-19T00:37:11Z"
  },
  {
    "school":"UCLA",
    "quality_z":-1.510143448,
    "game_value_z":0.8544519254,
    "market_z":0.0,
    "talent_prior_z":-0.5095087566,
    "solver_rating":1298.0537784637,
    "power_score":-0.6308436422,
    "power_rating":1399.065017244,
    "rank":114,
    "conference":"Big Ten",
    "abbreviation":"UCLA",
    "season":2025,
    "week":16,
    "as_of":"2026-06-19T00:37:11Z"
  },
  {
    "school":"Colorado",
    "quality_z":-1.0989881315,
    "game_value_z":-0.0581104168,
    "market_z":0.0,
    "talent_prior_z":-0.6830655424,
    "solver_rating":1248.3657995042,
    "power_score":-0.6463285131,
    "power_rating":1396.5874379109,
    "rank":115,
    "conference":"Big 12",
    "abbreviation":"COLO",
    "season":2025,
    "week":16,
    "as_of":"2026-06-19T00:37:11Z"
  },
  {
    "school":"Northern Illinois",
    "quality_z":-0.5579383033,
    "game_value_z":-1.2053318104,
    "market_z":0.0,
    "talent_prior_z":-0.2841217704,
    "solver_rating":1303.834855177,
    "power_score":-0.6519331754,
    "power_rating":1395.6906919398,
    "rank":116,
    "conference":"Mid-American",
    "abbreviation":"NIU",
    "season":2025,
    "week":16,
    "as_of":"2026-06-19T00:37:11Z"
  },
  {
    "school":"Wyoming",
    "quality_z":-0.7718209603,
    "game_value_z":-0.8515085306,
    "market_z":0.0,
    "talent_prior_z":0.1677942637,
    "solver_rating":1295.9078590952,
    "power_score":-0.6771691681,
    "power_rating":1391.6529331063,
    "rank":117,
    "conference":"Mountain West",
    "abbreviation":"WYO",
    "season":2025,
    "week":16,
    "as_of":"2026-06-19T00:37:11Z"
  },
  {
    "school":"App State",
    "quality_z":-0.6837396872,
    "game_value_z":-1.0874017631,
    "market_z":0.0,
    "talent_prior_z":-1.0203465575,
    "solver_rating":1324.1587399259,
    "power_score":-0.6916108634,
    "power_rating":1389.3422618631,
    "rank":118,
    "conference":"Sun Belt",
    "abbreviation":"APP",
    "season":2025,
    "week":16,
    "as_of":"2026-06-19T00:37:11Z"
  },
  {
    "school":"UAB",
    "quality_z":-0.9298035699,
    "game_value_z":-0.606368414,
    "market_z":0.0,
    "talent_prior_z":0.1841790664,
    "solver_rating":1286.4852486448,
    "power_score":-0.7002730387,
    "power_rating":1387.9563138129,
    "rank":119,
    "conference":"American Athletic",
    "abbreviation":"UAB",
    "season":2025,
    "week":16,
    "as_of":"2026-06-19T00:37:11Z"
  },
  {
    "school":"UL Monroe",
    "quality_z":-0.5116474545,
    "game_value_z":-1.5450644117,
    "market_z":0.0,
    "talent_prior_z":-0.0947422808,
    "solver_rating":1220.0357341623,
    "power_score":-0.7189393384,
    "power_rating":1384.9697058637,
    "rank":120,
    "conference":"Sun Belt",
    "abbreviation":"ULM",
    "season":2025,
    "week":16,
    "as_of":"2026-06-19T00:37:11Z"
  },
  {
    "school":"Colorado State",
    "quality_z":-1.2469779172,
    "game_value_z":-0.1054041396,
    "market_z":0.0,
    "talent_prior_z":-0.2963429444,
    "solver_rating":1224.0498632778,
    "power_score":-0.7442320812,
    "power_rating":1380.9228670096,
    "rank":121,
    "conference":"Mountain West",
    "abbreviation":"CSU",
    "season":2025,
    "week":16,
    "as_of":"2026-06-19T00:37:11Z"
  },
  {
    "school":"Southern Miss",
    "quality_z":-0.7042253007,
    "game_value_z":-1.2477300766,
    "market_z":0.0,
    "talent_prior_z":-0.5413647601,
    "solver_rating":1386.5758699475,
    "power_score":-0.7475119853,
    "power_rating":1380.3980823456,
    "rank":122,
    "conference":"Sun Belt",
    "abbreviation":"USM",
    "season":2025,
    "week":16,
    "as_of":"2026-06-19T00:37:11Z"
  },
  {
    "school":"Georgia State",
    "quality_z":-0.8564176773,
    "game_value_z":-0.955541056,
    "market_z":0.0,
    "talent_prior_z":0.0777727016,
    "solver_rating":1247.6635413536,
    "power_score":-0.7543384272,
    "power_rating":1379.3058516504,
    "rank":123,
    "conference":"Sun Belt",
    "abbreviation":"GAST",
    "season":2025,
    "week":16,
    "as_of":"2026-06-19T00:37:11Z"
  },
  {
    "school":"Temple",
    "quality_z":-1.3334637765,
    "game_value_z":-0.0314965212,
    "market_z":0.0,
    "talent_prior_z":0.574812762,
    "solver_rating":1356.1160856192,
    "power_score":-0.7734833,
    "power_rating":1376.2426719921,
    "rank":124,
    "conference":"American Athletic",
    "abbreviation":"TEM",
    "season":2025,
    "week":16,
    "as_of":"2026-06-19T00:37:11Z"
  },
  {
    "school":"New Mexico State",
    "quality_z":-0.6595243855,
    "game_value_z":-1.4704315546,
    "market_z":0.0,
    "talent_prior_z":-0.5918049927,
    "solver_rating":1284.4417446634,
    "power_score":-0.7832017606,
    "power_rating":1374.6877183043,
    "rank":125,
    "conference":"Conference USA",
    "abbreviation":"NMSU",
    "season":2025,
    "week":16,
    "as_of":"2026-06-19T00:37:11Z"
  },
  {
    "school":"Buffalo",
    "quality_z":-0.6764994956,
    "game_value_z":-1.5258733029,
    "market_z":0.0,
    "talent_prior_z":-0.0623194826,
    "solver_rating":1331.7494627176,
    "power_score":-0.8082055293,
    "power_rating":1370.6871153153,
    "rank":126,
    "conference":"Mid-American",
    "abbreviation":"BUF",
    "season":2025,
    "week":16,
    "as_of":"2026-06-19T00:37:11Z"
  },
  {
    "school":"San Jos\u00e9 State",
    "quality_z":-1.1332228017,
    "game_value_z":-0.881908152,
    "market_z":0.0,
    "talent_prior_z":-0.0792687889,
    "solver_rating":1168.1211029376,
    "power_score":-0.8928231357,
    "power_rating":1357.1482982855,
    "rank":127,
    "conference":"Mountain West",
    "abbreviation":"SJSU",
    "season":2025,
    "week":16,
    "as_of":"2026-06-19T00:37:11Z"
  },
  {
    "school":"Purdue",
    "quality_z":-2.0645847096,
    "game_value_z":0.898501039,
    "market_z":0.0,
    "talent_prior_z":-0.1463497864,
    "solver_rating":1246.7825535757,
    "power_score":-0.9367137349,
    "power_rating":1350.1258024135,
    "rank":128,
    "conference":"Big Ten",
    "abbreviation":"PUR",
    "season":2025,
    "week":16,
    "as_of":"2026-06-19T00:37:11Z"
  },
  {
    "school":"Charlotte",
    "quality_z":-2.0248739358,
    "game_value_z":0.2309075848,
    "market_z":0.0,
    "talent_prior_z":-0.9074936049,
    "solver_rating":1165.5383600727,
    "power_score":-1.0977809723,
    "power_rating":1324.3550444299,
    "rank":129,
    "conference":"American Athletic",
    "abbreviation":"CLT",
    "season":2025,
    "week":16,
    "as_of":"2026-06-19T00:37:11Z"
  },
  {
    "school":"Ball State",
    "quality_z":-1.5708090799,
    "game_value_z":-0.7410799347,
    "market_z":0.0,
    "talent_prior_z":-1.5668968819,
    "solver_rating":1236.1409724883,
    "power_score":-1.1050196664,
    "power_rating":1323.1968533786,
    "rank":130,
    "conference":"Mid-American",
    "abbreviation":"BALL",
    "season":2025,
    "week":16,
    "as_of":"2026-06-19T00:37:11Z"
  },
  {
    "school":"Rice",
    "quality_z":-1.7763077632,
    "game_value_z":-0.315198366,
    "market_z":0.0,
    "talent_prior_z":0.1832190387,
    "solver_rating":1171.2681932708,
    "power_score":-1.1056034462,
    "power_rating":1323.1034486064,
    "rank":131,
    "conference":"American Athletic",
    "abbreviation":"RICE",
    "season":2025,
    "week":16,
    "as_of":"2026-06-19T00:37:11Z"
  },
  {
    "school":"Syracuse",
    "quality_z":-2.049477188,
    "game_value_z":0.207065183,
    "market_z":0.0,
    "talent_prior_z":-0.7574376521,
    "solver_rating":1138.7351598255,
    "power_score":-1.1184579712,
    "power_rating":1321.0467246064,
    "rank":132,
    "conference":"ACC",
    "abbreviation":"SYR",
    "season":2025,
    "week":16,
    "as_of":"2026-06-19T00:37:11Z"
  },
  {
    "school":"UTEP",
    "quality_z":-1.0457684468,
    "game_value_z":-1.9129628691,
    "market_z":0.0,
    "talent_prior_z":0.5275576823,
    "solver_rating":1207.7267196499,
    "power_score":-1.1265977724,
    "power_rating":1319.7443564165,
    "rank":133,
    "conference":"Conference USA",
    "abbreviation":"UTEP",
    "season":2025,
    "week":16,
    "as_of":"2026-06-19T00:37:11Z"
  },
  {
    "school":"Coastal Carolina",
    "quality_z":-1.5951295474,
    "game_value_z":-0.8555818267,
    "market_z":0.0,
    "talent_prior_z":0.7668352874,
    "solver_rating":1206.3487859999,
    "power_score":-1.1505004896,
    "power_rating":1315.9199216605,
    "rank":134,
    "conference":"Sun Belt",
    "abbreviation":"CCU",
    "season":2025,
    "week":16,
    "as_of":"2026-06-19T00:37:11Z"
  },
  {
    "school":"Sam Houston",
    "quality_z":-1.2714190282,
    "game_value_z":-2.0717240998,
    "market_z":0.0,
    "talent_prior_z":0.6021298689,
    "solver_rating":1116.5668030932,
    "power_score":-1.2997399561,
    "power_rating":1292.0416070264,
    "rank":135,
    "conference":"Conference USA",
    "abbreviation":"SHSU",
    "season":2025,
    "week":16,
    "as_of":"2026-06-19T00:37:11Z"
  },
  {
    "school":"Massachusetts",
    "quality_z":-2.0564659177,
    "game_value_z":-2.4617357768,
    "market_z":0.0,
    "talent_prior_z":0.1179207726,
    "solver_rating":858.9428551639,
    "power_score":-1.857406822,
    "power_rating":1202.8149084829,
    "rank":136,
    "conference":"Mid-American",
    "abbreviation":"MASS",
    "season":2025,
    "week":16,
    "as_of":"2026-06-19T00:37:11Z"
  }
]